{"Đền Bà Chúa Kho (Hà Nội)":{"371553":{"diện tích":"1.700 m²","ngày nhận danh hiệu di tích tỉnh":"1983","loại di tích quốc gia":"Lịch sử - văn hóa","tiền tố":"Quản trưởng quốc khố công chúa","tên":"Đền Bà Chúa Kho","ngày nhận danh hiệu di tích quốc gia":"1994","hình":"[[File:Denthobachuakho.jpg|thumb|Hình ảnh bên ngoài Đền]]","tên thánh":"[[Bà Chúa Kho (Hà Nội)|Lý Thị Châu]]","loại di tích tỉnh":"Lịch sử - văn hóa }}","địa chỉ":"ngõ 129 [[đường Giảng Võ]], phường [[Giảng Võ]], quận [[Ba Đình]], thành phố [[Hà Nội]]"}},"Đình Chèm":{"108941":{"tên di tích đặc biệt":"Đình Chèm","chú thích":"Đình Chèm","tiền tố":"Thượng đẳng Thiên vương","lễ hội":"14 - 16 tháng 5 ÂL","tên thánh":"[[Lý Ông Trọng]]","hình":"Đình Chèm - NKS.jpg","cấp di tích":"đặc biệt }}","tên":"Đình Chèm","ngày nhận danh hiệu di tích đặc biệt":"25\/12\/2017","loại di tích đặc biệt":"kiến trúc","loại":"đình","địa chỉ":"phường Thụy Phương, quận Bắc Từ Liêm, Hà Nội","quyết định danh hiệu di tích đặc biệt":"2082\/QĐ-TTg"}},"Đình Mông Phụ":{"2433990":{"ngày nhận":"1984","chú thích":"Đình Mông Phụ nhìn từ cổng chính","hình":"Dinh mong phu.jpg","tên thánh":"[[Sơn Tinh]]","đóng cửa":"","công trạng":"","nguyên nhân đóng cửa":"","kinh độ":"105.4703084","tên di tích":"","mất":"","xây mới":"","xây dựng":"1533","địa chỉ":"thị xã [[Sơn Tây (thị xã)|Sơn Tây]], [[Hà Nội]]","tôn tạo":"","sinh":"","tiền tố":"Tản Viên Sơn Thánh","lễ hội":"","cấp di tích":"quốc gia","vĩ độ":"21.158403","quyết định":"}}","loại di tích 3":"","loại di tích 2":"văn hóa","tên":"Đình Mông Phụ","người sáng lập":"","loại di tích":"lịch sử"}},"Đền thờ Lê Hoàn":{"448649":{"ngày nhận":"2018","tôn tạo":"","sinh":"941","tiền tố":"Đại Hành Hoàng đế","lễ hội":"7 - 9 tháng 3 âm lịch","hình":"Đền Lê Hoàn.jpg","tên thánh":"[[Lê Hoàn]]","đóng cửa":"","công trạng":"Khai quốc hoàng đế [[nhà Tiền Lê]]","nguyên nhân đóng cửa":"","cấp di tích":"đặc biệt","vĩ độ":"19.973852","kinh độ":"105.534017","quyết định":"Quyết định số 1820\/QĐ-TTg }}","loại di tích 3":"","tên di tích":"Di tích kiến trúc nghệ thuật Đền thờ Lê Hoàn","loại di tích 2":"","mất":"1005","tên":"Đền thờ Lê Hoàn","xây mới":"","xây dựng":"","người sáng lập":"","địa chỉ":"Làng Trung Lập, xã [[Xuân Lập, Thọ Xuân|Xuân Lập]], huyện [[Thọ Xuân]], tỉnh [[Thanh Hóa]]","loại di tích":"kiến trúc"}},"Chùa Đồng Ngọ":{"3631090":{"image":"Cửu Phẩm Liên Hoa chùa Đồng Ngọ.jpg","chiều cao":"530 cm","nơi lưu trữ":"Chùa Đồng Ngọ, Hải Dương }}","image_size":"180px","chất liệu":"[[Gỗ]]","tiêu đề phụ":"''[[Bảo vật quốc gia (Việt Nam)#Đợt 5|Bảo vật quốc gia]] số 12, đợt 5''","name":"Cửu Phẩm Liên Hoa<br>chùa Đồng Ngọ","caption":"Đài Cửu Phẩm Liên Hoa đặt tại Nhà Phẩm chùa Đồng Ngọ","niên đại":"1692"}},"Đình Tân Hưng":{"387412":{"ngày nhận":"{{startdate|1992|8|4}}","tên khác":"","hình":"","tên thánh":"","đóng cửa":"","công trạng":"","nguyên nhân đóng cửa":"","kinh độ":"","tên di tích":"","mất":"","xây mới":"","xây dựng":"1907","địa chỉ":"Ấp Tân Hưng, xã [[Lý Văn Lâm (xã)|Lý Văn Lâm]], thành phố [[Cà Mau (thành phố)|Cà Mau]], tỉnh [[Cà Mau]]","tôn tạo":"","sinh":"","tiền tố":"","lễ hội":"Kỳ yên","cấp di tích":"quốc gia","vĩ độ":"","quyết định":"}}","loại di tích 3":"","loại di tích 2":"văn hóa","tên":"Đình Tân Hưng","người sáng lập":"","loại di tích":"lịch sử"}},"Bảo tàng Quảng Ninh":{"19729999":{"image":"An Sinh large glazed pot.jpg","image_size":"180px","chất liệu":"Gốm men","khối lượng":"126kg<ref name=\"BTQN\"\/>","caption":"Thống gốm hoa nâu An Sinh","kích thước":"","image2":"","chiều rộng":"đường kính miệng 107 - 108cm<br>đường kính đáy 68 - 69cm","thời điểm phát hiện":"2017<ref name=\"Nguyễn Văn Anh\">{{Chú thích báo|tác giả=Nguyễn Văn Anh, Đặng Hồng Sơn |url=https:\/\/vjst.vn\/vn\/tin-tuc\/1378\/kham-pha-khao-co-hoc-tieu-bieu--tai-khu-di-tich-nha-tran-o-dong-trieu--quang-ninh-.aspx |tên bài=Khám phá khảo cổ học tiêu biểu tại khu di tích nhà Trần ở Đông Triều, Quảng Ninh |thành phố=Hà Nội |nhà xuất bản=Tạp chí Khoa học và Công nghệ|ngày=10 tháng 7 năm 2018 |ngày truy cập=30 tháng 6 năm 2022 | url lưu trữ=| ngày lưu trữ=}}<\/ref>","chiều dày":"","chiều cao":"71,5 - 73cm<ref name=\"BTQN\">{{Chú thích web|tác giả=Bảo tàng Quảng Ninh |url=http:\/\/www.baotangquangninh.vn\/Chuyen-de\/bao-vat-quoc-gia-thong-gom-hoa-nau-an-sinh-o-bao-tang-quang-ninh-1093.htm|tên bài=Bảo vật Quốc gia Thống gốm hoa nâu An Sinh ở Bảo tàng Quảng Ninh |nhà xuất bản=Bảo tàng Quảng Ninh |năm=2022 |ngày truy cập=30 tháng 6 năm 2022 | url lưu trữ=| ngày lưu trữ=}}<\/ref>","nơi lưu trữ":"Bảo tàng Quảng Ninh","địa điểm phát hiện":"[[Đền An Sinh]]","tiêu đề phụ":"''[[Bảo vật quốc gia (Việt Nam)#Đợt 8|Bảo vật quốc gia]] số 13, đợt 10''","name":"Thống gốm hoa nâu An Sinh","image2_size":"","số đăng ký":"}}","niên đại":"thế kỉ XIII","phát hiện bởi":"[[Trường Đại học Khoa học Xã hội và Nhân văn, Đại học Quốc gia Hà Nội|Đại học Khoa học Xã hội và Nhân văn]]","hệ chữ viết":"","thời kỳ\/văn hóa":"[[Thời Trần]]","chiều dài":""}},"Cầu Núi Đọ":{"19719363":{"chi phí":"Khoảng 550 tỷ [[Đồng (đơn vị tiền tệ)|đồng]]","độ cao gầm cầu":"1,75 \u2013 5,4 m","tổng thầu":"[[Tổng công ty Cổ phần Xuất nhập khẩu và Xây dựng Việt Nam|Vinaconex]] \u2013 Trung Nam E&C","kiểu":"[[Cầu dầm]]","tọa độ":"{{coord|19.887736|105.730904|type:landmark|format=dms|name=Cầu Núi Đọ|display=title,inline}}","tuyến đường":"{{Banner đường Việt Nam|CT|01|link=1}} {{AHN-AH|1|VN}} [[Đường cao tốc Mai Sơn \u2013 Quốc lộ 45]]","hình":"Núi Đọ Bridge in January, 2023.jpg","sông":"[[Sông Chu]]","chiều rộng":"23,5 m","số nhịp":"39 nhịp (3 nhịp đúc hẫng và 36 nhịp dầm Super T)","vật liệu":"[[Bê tông cốt thép]] dự ứng lực","khởi công":"{{start date|2021|3|30}}","extra":"{{maplink|frame=yes|frame-width=250|zoom=15|type=point}} }}","lanes":"4 làn xe cơ giới, 2 làn dân sinh hỗn hợp","tên":"Cầu Núi Đọ","hoàn thành":"{{end date|2023|4|29}}","ghi chú hình":"Cầu Núi Đọ nhìn từ xã [[Thiệu Hợp]], tháng 1 năm 2023","quốc gia":"{{VIE}}","vị trí":"Huyện [[Thiệu Hóa]], tỉnh [[Thanh Hóa]]","chiều dài":"1.646,9 m"}},"Miếu Thượng (Đặng Xá)":{"2262723":{"tiền tố":"Bạch Mã Đại Vương","tên":"Miếu Thượng","xây dựng":"[[Thời Đinh]] }}","tên thánh":"[[Linh Lang]]","địa chỉ":"thôn Đặng Xá, xã [[Văn Xá]], huyện [[Kim Bảng]], tỉnh [[Hà Nam]]"}},"Đình Quan Lạn":{"564682":{"quyết định danh hiệu di tích quốc gia":"575\/QĐ-VHTT }}","sinh":"1136","tên di tích quốc gia":"Đình, Chùa, Miếu, Nghè Quan Lạn","loại di tích quốc gia":"Lịch sử - văn hóa","tiền tố":"Hoàng đế","mất":"1175","tên":"Đình Quan Lạn","ngày nhận danh hiệu di tích quốc gia":"14\/7\/1990","loại di tích quốc gia 2":"Kiến trúc nghệ thuật","hình":"Quan Lạn communal house.JPG","tên thánh":"[[Lý Anh Tông]]","địa chỉ":"xã Quan Lạn, huyện Vân Đồn, tỉnh Quảng Ninh"}},"Đình Yên Sở":{"257827":{"tên khác":"Quán Giá, Đền Quán Giá, Đền Giá, Quán Diễm Xá","chú thích":"Tiền đường Đình Yên Sở","sinh":"''không rõ''","tiền tố":"Phục Man Tướng Quân","mất":"547","lễ hội":"10 tháng 3 ÂL }}","tên":"Đình Yên Sở","xây dựng":"thời [[Lý Thái Tổ]]","hình":"Đình yên sở tiền đường.jpg","tên thánh":"[[Lý Phục Man]]","địa chỉ":"làng Yên Sở, xã [[Yên Sở]], huyện [[Hoài Đức]], thành phố [[Hà Nội]]","được thờ vì":"Danh tướng của [[Lý Nam Đế]]"}},"Đền_Voi_Phục":{"137378":{"ngày nhận":"28 tháng 4 năm 1962","ngày tước":"","chú thích":"Tượng con voi phủ phục tại Đền","hình":"Đền Voi Phục.JPG","tên thánh":"[[Linh Lang]]","điện thoại":"","công trạng":"tướng quân đánh Tống","kinh giây":"","tên di tích":"Đền Voi Phục","mất":"?","sinh 2":"?","xây mới":"","loại":"","địa chỉ":"362 phố [[Kim Mã]], phường [[Ngọc Khánh]], quận [[Ba Đình]], thành phố [[Hà Nội]]","tước vị 2":"Thứ phi của Lý Thái Tông","tên di tích đặc biệt":"Thăng Long tứ trấn","vĩ giây":"","sinh":"1064","thành lập":"1065","lễ hội":"9 và 10 tháng hai âm lịch","công trạng 2":"","vĩ độ":"","quyết định":"313-VH\/VP<ref>{{Chú thích web|url=https:\/\/thuvienphapluat.vn\/van-ban\/Van-hoa-Xa-hoi\/Quyet-dinh-313-VH-VP-xep-hang-nhung-di-tich-danh-thang-canh-toan-mien-Bac-19864.aspx|title=Quyết định 313-VH\/VP xếp hạng những di tích, danh thắng cảnh toàn miền Bắc|website=Thư viện pháp luật}}<\/ref>","đối tượng thờ":"nhân vật lịch sử","tên":"Đền Voi Phục","ngày nhận danh hiệu di tích đặc biệt":"18 tháng 1 năm 2022","quyết định danh hiệu di tích đặc biệt":"93\/QĐ-TTg<ref>{{Chú thích web|url=http:\/\/dsvh.gov.vn\/quyet-dinh-xep-hang-di-tich-quoc-gia-dac-biet-dot-12-3450|tựa đề=Quyết định xếp hạng di tích quốc gia đặc biệt (đợt 12)|tác giả=Đức Dũng|website=Cục di sản văn hóa|url-status=live}}<\/ref>","loại di tích đặc biệt 2":"Kiến trúc nghệ thuật","loại di tích":"lịch sử","thánh tích 2":"","mất 2":"?","đóng cửa":"","tiêu chuẩn":"","kinh độ":"","web":"","vĩ phút":"","tên thánh 2":"Dương Thị Quang","tôn tạo":"","một phần của di tích (đặc biệt)":"Thăng Long tứ trấn","một phần của":"}}","loại đền":"","kinh phút":"","thánh tích":"","hồ sơ tham khảo":"","tước vị":"Hoàng tử","cấp di tích":"quốc gia","loại di tích 3":"","loại di tích 2":"văn hóa","loại di tích đặc biệt":"Lịch sử - văn hóa","người sáng lập":""}},"Bia Xá Lợi Tháp Minh":{"14130576":{"image":"Xá Lợi Tháp Minh stele.jpg","image_size":"230px","chất liệu":"[[Đá]]","caption":"","kích thước":"Thân bia: 53,5cm x 45cm x 8,5cm<br> Nắp bia: 53,5cm x 45cm x 4cm","thời điểm phát hiện":"2004","nơi lưu trữ":"Bảo tàng tỉnh Bắc Ninh","địa điểm phát hiện":"thôn Xuân Quan, [[Trí Quả]], [[Thuận Thành]], [[Bắc Ninh]]","tiêu đề phụ":"''[[Bảo vật quốc gia (Việt Nam)#Đợt 2|Bảo vật quốc gia]] số 7, đợt 2''","name":"Bia Xá Lợi Tháp<br>舍利塔銘碑","số đăng ký":"2135<ref name=\"Cuc di san\">[http:\/\/dsvh.gov.vn\/bia-xa-loi-thap-minh-3043 Bia \u201CXá lợi Tháp Minh\u201D, Hồ sơ di sản, tư liệu Cục Di sản văn hóa, truy cập 5 tháng 5 năm 2020]<\/ref> }}","niên đại":"601","phát hiện bởi":"Nguyễn Văn Đức","hệ chữ viết":"[[Chữ Hán]]","thời kỳ\/văn hóa":"[[Nhà Tùy]]"}},"Đền Bà Chúa Kho (Hưng Yên)":{"14530900":{"ngày nhận":"","tên khác":"Thương Tỉnh linh từ <br> Đền Gốc Sanh","hình":"","tên thánh":"[[Lê Bạch Nương]]","đóng cửa":"","công trạng":"Bảo vệ kho ngân khố trong chiến tranh","nguyên nhân đóng cửa":"","kinh độ":"106.0849929","tên di tích":"","mất":"","xây mới":"","xây dựng":"[[Nhà Lê trung hưng]]","địa chỉ":"Số 348, Đường Bà Chúa Kho, khu phố Điện Biên III, [[Quang Trung, thành phố Hưng Yên|Quang Trung]], [[Hưng Yên (thành phố)|Hưng Yên]], [[Hưng Yên]]","tôn tạo":"","sinh":"","tiền tố":"Bà chúa kho","lễ hội":"Lễ Bà Chúa Kho: 01 - 03 tháng 03 âm lịch","cấp di tích":"đặc biệt","vĩ độ":"21.2049788","quyết định":"}}","loại di tích 3":"","loại di tích 2":"","tên":"Đền Bà Chúa Kho","người sáng lập":"","loại di tích":""}},"Dinh Cô":{"2308291":{"diện tích":"1.000 m2","chú thích":"Toàn cảnh Dinh Cô trên đồi Kỳ Vân","quyết định danh hiệu di tích quốc gia":"65QĐ\/BT }}","loại di tích quốc gia":"Lịch sử - văn hóa","tiền tố":"Long Hải Thần Nữ","lễ hội":"10-12 tháng 2 ÂL","tên":"Dinh Cô","ngày nhận danh hiệu di tích quốc gia":"16 tháng 1 năm 1995","xây dựng":"cuối thế kỷ 18","hình":"Dinh Cô (toàn cảnh).jpg","tên thánh":"[[Lê Thị Hồng]]","địa chỉ":"thị trấn [[Long Hải]], huyện [[Long Điền]], tỉnh [[Bà Rịa \u2013 Vũng Tàu]]"}},"Đền Ngọc Quế":{"19594214":{"ngày nhận":"30 tháng 10 năm 1990","ngày tước":"","chú thích":"Đền Ngọc Quế","hình":"Den_Ngoc_Que.jpg","tên thánh":"[[Đỗ Huyến]]","điện thoại":"","đóng cửa":"","công trạng":"","di tích":"[[Di tích lịch sử văn hóa quốc gia]]","kinh giây":"24","nguyên nhân đóng cửa":"","tiêu chuẩn":"","kinh độ":"106","web":"","mất":"?","vĩ phút":"41","xây mới":"","loại":"","địa chỉ":"thôn [[Ngọc Quế]], xã [[Quỳnh Hoa]], huyện [[Quỳnh Phụ]], tỉnh [[Thái Bình]]","quyết định 2":"","tôn tạo":"","vĩ giây":"41","một phần của":"","sinh":"?","loại đền":"","hồ sơ tham khảo 2":"","thành lập":"","kinh phút":"19","lễ hội":"8 tháng 8 âm lịch","thánh tích":"","hồ sơ tham khảo":"","tước vị":"","tên thần":"","cấp di tích":"quốc gia","ngày nhận 2":"","vĩ độ":"20","một phần của 2":"}}","quyết định":"1214<ref>[http:\/\/thaibinhtv.vn\/news\/89\/31295\/le-hoi-den-ngoc-que Lễ hội Đền Ngọc Quế], Đài Phát Thanh Và Truyền Hình Thái Bình, 19 tháng 08 năm 2016.<\/ref>.","loại di tích 3":"","đối tượng thờ":"nhân vật huyền sử","loại di tích 2":"văn hóa","tên":"Đền Ngọc Quế","tiêu chuẩn 2":"","người sáng lập":"","loại di tích":"lịch sử"}},"Cầu Xương Giang":{"19512073":{"khởi công":"[[1998]]","tên":"Cầu Xương Giang","tuyến đường":"{{Banner đường Việt Nam|CT|01|link=2}}<br>{{Banner đường Việt Nam|QL|1}}","sông":"[[Sông Thương]]","chiều rộng":"14 m","chiều dài":"306,2 m","khánh thành":"[[31 tháng 12]] năm [[2000]] }}"}},"Đình thần Bình Thủy":{"2449544":{"ngày nhận":"","tên khác":"","hình":"Đình thần Bình Thủy.JPG","tên thánh":"Thượng đẳng thần Lễ Thành hầu Nguyễn Hữu Cảnh","đóng cửa":"","công trạng":"","nguyên nhân đóng cửa":"","kinh độ":"105.3197908","tên di tích":"","mất":"","xây mới":"","xây dựng":"1783","địa chỉ":"Xã [[Bình Thủy (xã)|Bình Thủy]], huyện [[Châu Phú]], tỉnh [[An Giang]]","tôn tạo":"1972","sinh":"","tiền tố":"","lễ hội":"[[Lễ Kỳ yên]]","cấp di tích":"","vĩ độ":"10.516632","quyết định":"}}","loại di tích 3":"","loại di tích 2":"nghệ thuật","tên":"Đình thần Bình Thủy","ghi chú hình":"Đình thần Bình Thủy","người sáng lập":"Dương Văn Hoá","loại di tích":"kiến trúc"}},"Đình Chu Quyến":{"565184":{"ngày nhận":"28 tháng 4 năm 1962","chú thích":"Đình Chu Quyến","hình":"Đình Tràng.JPG","tên thánh":"[[Nhã Lang Vương|Nhã Lang]]","điện thoại":"","đóng cửa":"","công trạng":"","tiêu chuẩn":"","kinh độ":"105.442898","web":"","tên di tích":"Đình Chu Quyến","mất":"","xây mới":"","loại":"đình","địa chỉ":"","tôn tạo":"","một phần của":"}}","sinh":"","loại đền":"","thành lập":"[[thế kỷ 17]]","lễ hội":"","thánh tích":"","hồ sơ tham khảo":"","tước vị":"Nhã Lang vương","cấp di tích":"quốc gia","vĩ độ":"21.196232","quyết định":"313-VH\/VP<ref>{{Chú thích web|url=https:\/\/thuvienphapluat.vn\/van-ban\/Van-hoa-Xa-hoi\/Quyet-dinh-313-VH-VP-xep-hang-nhung-di-tich-danh-thang-canh-toan-mien-Bac-19864.aspx|title=Quyết định 313-VH\/VP xếp hạng những di tích, danh thắng cảnh toàn miền Bắc|website=Thư viện pháp luật}}<\/ref>","loại di tích 3":"","đối tượng thờ":"nhân vật lịch sử","loại di tích 2":"văn hóa","tên":"Đình Chu Quyến","người sáng lập":"","loại di tích":"lịch sử"}},"Đền Kỳ Cùng":{"2197279":{"ngày nhận":"{{startdate|1993}}","bản đồ 1":"","tên khác":"Đền Quan Lớn Tuần Tranh","chú thích":"Đền Kỳ Cùng","hình":"Đền Kỳ Cùng.jpg","tên thánh":"Quan Lớn Tuần Tranh","điện thoại":"","đóng cửa":"","công trạng":"Nắm quyền trấn giữ miền duyên hải sông Tranh","di tích":"[[Di tích quốc gia]]","kinh độ":"","web":"","tên di tích":"Đền Kỳ Cùng","mất":"","xây mới":"","ghi chú bản đồ 1":"","địa chỉ":"Đường Trần Đăng Ninh, [[Vĩnh Trại]], [[Lạng Sơn (thành phố)|Lạng Sơn]], [[Lạng Sơn]]","quốc gia":"{{VIE}}","tôn tạo":"Năm 1928, 1931, 1967","sinh":"","loại đền":"","thành lập":"","lễ hội":"22-27\/1 (âl)","thánh tích":"","tước vị":"","cấp di tích":"quốc gia","vĩ độ":"","quyết định":"}}","đối tượng thờ":"","tên":"Đền Kỳ Cùng","người sáng lập":"","loại di tích":"lịch sử văn hóa"}},"Lễ tế giao":{"19159556":{"image":"越南阮朝弘宗宣皇帝阮福晙（启定1916年\u20141925年）31岁登基时的冕服照片（1916年）.jpg","nơi lưu trữ":"[[Bảo tàng Cổ vật Cung đình Huế]] }}","image_size":"200px","chất liệu":"Vải sa","tiêu đề phụ":"''[[Bảo vật quốc gia (Việt Nam)#Đợt 4|Bảo vật quốc gia]] số 25, đợt 4","name":"Áo tế giao triều Nguyễn","caption":"Vua [[Khải Định]] mặc trang phục Cổn Miện (1916)","niên đại":"1802","chiều rộng":"98 cm","thời kỳ\/văn hóa":"[[Nhà Nguyễn]]","chiều dài":"117 cm"}},"Chùa Côn Sơn":{"29675":{"image":"Côn Sơn Tư Phúc tự bi stele.jpg","chiều cao":"1,2m","image_size":"230px","chất liệu":"[[Đá]] Kính Chủ","tiêu đề phụ":"''[[Bảo vật quốc gia (Việt Nam)#Đợt 6|Bảo vật quốc gia]] số 14, đợt 6''","name":"Bia Côn Sơn Tư Phúc tự bi<br>崑山資福寺碑","caption":"Bia Côn Sơn Tư Phúc tự bi","niên đại":"1607","chiều rộng":"32cm","hệ chữ viết":"[[Chữ Hán]]","thời kỳ\/văn hóa":"[[Nhà Lê trung hưng]] }}"}},"Đền Xưa":{"19762463":{"tên di tích đặc biệt":"Đền Xưa - Chùa Giám - Đền Bia","một phần của di tích (đặc biệt)":"Cụm di tích Đền Xưa - [[Chùa Giám]] - [[Đền Bia]]","sinh":"1330","tiền tố":"Đại danh y \u2013 Thiền sư","tên thánh":"[[Tuệ Tĩnh]]","vĩ độ":"20.971130","kinh độ":"106.246972","mất":"1400","tên":"Đền Xưa","ngày nhận danh hiệu di tích đặc biệt":"25 tháng 12, 2017","loại di tích đặc biệt":"Lịch sử - văn hóa","địa chỉ":"thôn Nghĩa Phú, xã [[Cẩm Vũ]], huyện [[Cẩm Giàng]], tỉnh [[Hải Dương]]","quyết định danh hiệu di tích đặc biệt":"2082\/QĐ-TTg }}","được thờ vì":"Danh y"}},"Đền Tử Đồng Đế Quân":{"18171371":{"tên khác":"Đền Thượng","tên":"Đền Tử Đồng Đế Quân","hình":"Đền Tử Đồng Đế Quân nhìn từ dưới cổng chùa lên..jpg","tên thánh":"[[Văn Xương Đế Quân]]","người sáng lập":"[[Nguyễn Địch Tâm]] }}","địa chỉ":"[[Núi Hoàng Xá]], thị trấn [[Quốc Oai]], huyện [[Quốc Oai]], [[Hà Nội]]"}},"Văn miếu Mao Điền":{"77158":{"tên di tích đặc biệt":"Văn miếu Mao Điền","vĩ giây":"6","quyết định danh hiệu di tích quốc gia":"97\/QĐ-VH }}","sinh":"551 TCN","tên di tích quốc gia":"Văn miếu Mao Điền","kinh phút":"11","hình":"Văn miếu Mao Điền.jpg","tên thánh":"[[Khổng Tử]]","kinh giây":"10","vĩ độ":"20","kinh độ":"106","loại di tích quốc gia":"Lịch sử - văn hóa","mất":"479 TCN","tên":"Văn miếu Mao Điền","ngày nhận danh hiệu di tích đặc biệt":"25 tháng 11 năm 2017","vĩ phút":"56","ngày nhận danh hiệu di tích quốc gia":"1992","xây dựng":"thời Lê sơ","loại di tích đặc biệt":"Lịch sử - văn hóa","địa chỉ":"làng Mậu Tài, xã [[Cẩm Điền]], huyện [[Cẩm Giàng]], [[Hải Dương]]","quyết định danh hiệu di tích đặc biệt":"{{URL|http:\/\/vanban.chinhphu.vn\/portal\/page\/portal\/chinhphu\/hethongvanban?class_id=2&_page=1&mode=detail&document_id=192339|2082\/QĐ-TTg}}"}},"Bia Võ Cạnh":{"19138521":{"image":"Vo Canh stele (National Museum of Vietnamese History).jpg","image_size":"180px","chất liệu":"[[Sa thạch]]","caption":"Bia Võ Cạnh tại Bảo tàng lịch sử Quốc gia","chiều rộng":"110 cm","thời điểm phát hiện":"1910","chiều dày":"80 cm","chiều cao":"320 cm","nơi lưu trữ":"[[Bảo tàng Lịch sử Quốc gia (Việt Nam)|Bảo tàng Lịch sử Quốc gia]]","địa điểm phát hiện":"làng Võ Cạnh, [[Vĩnh Trung, Nha Trang]]","tiêu đề phụ":"''[[Bảo vật quốc gia (Việt Nam)#Đợt 2|Bảo vật quốc gia]] số 23, đợt 2''","name":"Bia Võ Cạnh","số đăng ký":"LSb.32864<ref name=\"Cuc di san\">[http:\/\/dsvh.gov.vn\/bia-vo-canh-3065 Bia Võ Cạnh, Hồ sơ di sản, tư liệu Cục Di sản văn hóa, truy cập 23 tháng 4 năm 2020]<\/ref> }}","niên đại":"Khoảng thế kỷ II - III","phát hiện bởi":"","hệ chữ viết":"[[Chữ Phạn]]","thời kỳ\/văn hóa":"[[Chăm Pa]]"}},"Miếu Lịch đại đế vương":{"18992854":{"ngày nhận":"","hình":"Miếu Lịch đại đế vương.jpg","tên thánh":"","đóng cửa":"","công trạng":"","nguyên nhân đóng cửa":"","danh sách":"#Lịch sử","kinh độ":"","tên di tích":"","mất":"","xây mới":"","xây dựng":"1823","loại":"miếu","địa chỉ":"[[Lịch Đợi]], [[Phường Đúc]], [[Huế]]","tôn tạo":"","sinh":"","tình trạng":"phế tích }}","tiền tố":"","lễ hội":"tháng 2 âm lịch","cấp di tích":"","tên gốc":"歷代帝王廟","vĩ độ":"","quyết định":"","loại di tích 3":"","loại di tích 2":"","thờ phụng":"Lịch đại đế vương","tên":"Miếu Lịch đại đế vương","người sáng lập":"[[Minh Mạng]]","loại di tích":""}},"Đình thần Châu Phú":{"238392":{"ngày nhận":"{{startdate|1988|11|16}}","mất 2":"1829","tên khác":"Trung Nghĩa Từ, Đình thần Châu Phú, Lễ Công Từ Đường (Đền Lễ Công), Đền Ông","hình":"Cổng đình thần Châu Phú.jpg","tên thánh":"[[Nguyễn Hữu Cảnh]]","tiền tố 3":"Chánh phó","đóng cửa":"","công trạng":"Danh tướng thời chúa [[Nguyễn Phúc Chu]]","tiền tố 2":"Trung đẳng thần","nguyên nhân đóng cửa":"","kinh độ":"","tên di tích":"","mất":"1700","sinh 2":"1761","xây mới":"1926","xây dựng":"","địa chỉ":"Góc đường Trần Hưng Đạo \u2013 Nguyễn Văn Thoại, phường [[Châu Phú A]], thành phố [[Châu Đốc]], tỉnh [[An Giang]]","tên thánh 2":"[[Thoại Ngọc Hầu]]","tên thánh 3":"[[Vệ Thủy]]","tôn tạo":"1838 \u2013 1858","sinh":"1650","tiền tố":"Thượng đẳng thần","lễ hội":"[[Lễ Kỳ yên]]","cấp di tích":"quốc gia","tên gốc":"忠義祠","vĩ độ":"","quyết định":"Số 1288\/VH-QĐ }}","tên":"Đình Châu Phú","người sáng lập":"[[Thoại Ngọc hầu|Nguyễn Văn Thoại]]","loại di tích":"kiến trúc nghệ thuật"}},"Đàn Nam Giao (Thăng Long)":{"19167715":{"image":"Nam Giao stele.jpg","image_size":"280px","chất liệu":"[[Đá]]","caption":"Bia điện Nam Giao tại Bảo tàng lịch sử Quốc gia","kích thước":"Đế: 214 cm x 156 cm x 51 cm","chiều rộng":"146 cm","chiều dày":"34 cm","chiều cao":"213 cm","nơi lưu trữ":"[[Bảo tàng Lịch sử Quốc gia (Việt Nam)|Bảo tàng Lịch sử Quốc gia]]","tiêu đề phụ":"''[[Bảo vật quốc gia (Việt Nam)#Đợt 4|Bảo vật quốc gia]] số 17, đợt 4''","name":"Bia điện Nam Giao <br>南郊殿碑記","số đăng ký":"LSb.32852<ref name=\"Bao tang lich su\" \/> }}","niên đại":"1679","hệ chữ viết":"[[Chữ Hán]]","thời kỳ\/văn hóa":"[[Nhà Lê Trung Hưng]]"}},"Đình Phú Vĩnh":{"19625908":{"ngày nhận":"","hình":"Miếu Hỏa Thần.png","tên thánh":"","đóng cửa":"","công trạng":"","nguyên nhân đóng cửa":"","danh sách":"#Lịch sử","kinh độ":"","tên di tích":"","mất":"","xây mới":"","xây dựng":"1825","loại":"miếu","địa chỉ":"Lịch Đợi, [[Phường Đúc]], [[Huế]]","tôn tạo":"1903, 1937","sinh":"","tình trạng":"bỏ hoang }}","tiền tố":"","lễ hội":"23 tháng 6 âm lịch","cấp di tích":"","tên gốc":"","vĩ độ":"","quyết định":"","loại di tích 3":"","loại di tích 2":"","thờ phụng":"Thần lửa, thần hỏa pháo","tên":"Miếu Hỏa Thần","người sáng lập":"[[Minh Mạng]]","loại di tích":""}},"Đền Voi Phục":{"137378":{"ngày nhận":"28 tháng 4 năm 1962","ngày tước":"","chú thích":"Tượng con voi phủ phục tại Đền","hình":"Đền Voi Phục.JPG","tên thánh":"[[Linh Lang]]","điện thoại":"","công trạng":"tướng quân đánh Tống","kinh giây":"","tên di tích":"Đền Voi Phục","mất":"?","sinh 2":"?","xây mới":"","loại":"","địa chỉ":"362 phố [[Kim Mã]], phường [[Ngọc Khánh]], quận [[Ba Đình]], thành phố [[Hà Nội]]","tước vị 2":"Thứ phi của Lý Thái Tông","tên di tích đặc biệt":"Thăng Long tứ trấn","vĩ giây":"","sinh":"1064","thành lập":"1065","lễ hội":"9 và 10 tháng hai âm lịch","công trạng 2":"","vĩ độ":"","quyết định":"313-VH\/VP<ref>{{Chú thích web|url=https:\/\/thuvienphapluat.vn\/van-ban\/Van-hoa-Xa-hoi\/Quyet-dinh-313-VH-VP-xep-hang-nhung-di-tich-danh-thang-canh-toan-mien-Bac-19864.aspx|title=Quyết định 313-VH\/VP xếp hạng những di tích, danh thắng cảnh toàn miền Bắc|website=Thư viện pháp luật}}<\/ref>","đối tượng thờ":"nhân vật lịch sử","tên":"Đền Voi Phục","ngày nhận danh hiệu di tích đặc biệt":"18 tháng 1 năm 2022","quyết định danh hiệu di tích đặc biệt":"93\/QĐ-TTg<ref>{{Chú thích web|url=http:\/\/dsvh.gov.vn\/quyet-dinh-xep-hang-di-tich-quoc-gia-dac-biet-dot-12-3450|tựa đề=Quyết định xếp hạng di tích quốc gia đặc biệt (đợt 12)|tác giả=Đức Dũng|website=Cục di sản văn hóa|url-status=live}}<\/ref>","loại di tích đặc biệt 2":"Kiến trúc nghệ thuật","loại di tích":"lịch sử","thánh tích 2":"","mất 2":"?","đóng cửa":"","tiêu chuẩn":"","kinh độ":"","web":"","vĩ phút":"","tên thánh 2":"Dương Thị Quang","tôn tạo":"","một phần của di tích (đặc biệt)":"Thăng Long tứ trấn","một phần của":"}}","loại đền":"","kinh phút":"","thánh tích":"","hồ sơ tham khảo":"","tước vị":"Hoàng tử","cấp di tích":"quốc gia","loại di tích 3":"","loại di tích 2":"văn hóa","loại di tích đặc biệt":"Lịch sử - văn hóa","người sáng lập":""}},"Văn miếu Xích Đằng":{"293682":{"mất 2":"1370","bản đồ 1":"","tên khác":"","chú thích":"Nghi môn Văn miếu Xích Đằng","tên di tích quốc gia":"Quần thể di tích Văn miếu Xích Đằng","hình":"Văn miếu Xích Đằng 02.JPG","tên thánh":"[[Khổng Tử]]","điện thoại":"","đóng cửa":"","công trạng":"","kinh giây":"56","tiền tố 2":"Văn Trinh Công","kinh độ":"106","web":"","loại di tích quốc gia":"lịch sử","mất":"479 TCN","vĩ phút":"39","ngày nhận danh hiệu di tích quốc gia":"1992","sinh 2":"1292","xây mới":"","ghi chú bản đồ 1":"","loại":"văn miếu","địa chỉ":"thôn Xích Đằng, phường [[Lam Sơn, thành phố Hưng Yên|Lam Sơn]], [[hưng Yên (thành phố)|thành phố Hưng Yên]], tỉnh [[Hưng Yên]]","tên thánh 2":"[[Chu Văn An]]","tôn tạo":"1839","vĩ giây":"43","sinh":"551 TCN","loại đền":"","thành lập":"1832","tiền tố":"Vạn thế sư biểu","kinh phút":"2","lễ hội":"4 - 5 tháng Giêng âm lịch","thánh tích":"","cấp di tích":"quốc gia }}","vĩ độ":"20","đối tượng thờ":"","tên":"Văn miếu Xích Đằng","người sáng lập":""}},"Đường Kách mệnh":{"447953":{"image":"File:Duong Kach Menh (Original).jpg","image_size":"230px","chất liệu":"Giấy nến","caption":"Bản gốc Đường Kách mệnh in năm 1927","kích thước":"Trang bìa: 15cm x 20cm <br> Trang sách: 15cm x 22cm","thời điểm phát hiện":"1958","nơi lưu trữ":"Bảo tàng Lịch sử Quốc gia","địa điểm phát hiện":"[[Tòa án nhân dân tối cao (Việt Nam)|Tòa án nhân dân tối cao]]","tiêu đề phụ":"''[[Bảo vật quốc gia (Việt Nam)#Đợt 1|Bảo vật quốc gia]] số 9, đợt 1''","name":"Cuốn ''Đường Kách mệnh''","số đăng ký":"}}","niên đại":"1927","phát hiện bởi":"Nguyễn Văn Hoan","hệ chữ viết":"[[Chữ Quốc ngữ]]","thời kỳ\/văn hóa":"[[Pháp thuộc]]"}},"Chùa Thanh Mai":{"1752770":{"image":"Chua Thanh Mai 2.jpg","image_size":"250px","chất liệu":"[[Đá]]","caption":"Bia \"Thanh Mai Viên Thông tháp bi\" (lớn hơn, bên phải)","chiều rộng":"82 cm","chiều dày":"14 cm","chiều cao":"131 cm","nơi lưu trữ":"Chùa Thanh Mai, [[Hải Dương]] }}","tiêu đề phụ":"''[[Bảo vật quốc gia (Việt Nam)#Đợt 5|Bảo vật quốc gia]] số 6, đợt 5''","name":"Bia \"Thanh Mai Viên Thông tháp bi\"<br>青梅圓通塔碑","niên đại":"1362","hệ chữ viết":"[[Chữ Hán]]","thời kỳ\/văn hóa":"[[Thời Trần]]"}},"Đình Tân Thạch":{"1705623":{"ngày nhận":"{{startdate|2001|12|28}}","tên khác":"Đình Thạch Hồ","tôn tạo":"","sinh":"","tiền tố":"","lễ hội":"[[Lễ Kỳ yên]]","hình":"Cổng đình Tân Thạch.jpg","tên thánh":"[[Thành hoàng]]","đóng cửa":"","công trạng":"","nguyên nhân đóng cửa":"","cấp di tích":"quốc gia","tên gốc":"疆無壽聖","vĩ độ":"","kinh độ":"","quyết định":"Số 52\/2001\/QĐ-BVHTT }}","tên di tích":"Đình Tân Thạch","mất":"","tên":"Đình Tân Thạch","xây mới":"","xây dựng":"1841","người sáng lập":"Nguyễn Quý Bằng","địa chỉ":"Ấp 9, [[Tân Thạch]], [[Châu Thành, Bến Tre|Châu Thành]], [[Bến Tre]]","loại di tích":"kiến trúc nghệ thuật"}},"Đình So":{"3703781":{"chú thích":"","tên di tích quốc gia":"Đình So","hình":"Đình So.png","tên thánh":"","đóng cửa":"","công trạng":"","nguyên nhân đóng cửa":"","kinh độ":"","loại di tích quốc gia":"Kiến trúc nghệ thuật","mất":"","xây mới":"","ngày nhận danh hiệu di tích quốc gia":"10 tháng 7 năm 1980","xây dựng":"","địa chỉ":"làng Sơn Lộ, xã Cộng Hòa, Quốc Oai, Hà Nội","tên di tích đặc biệt":"Đình So","tôn tạo":"","quyết định danh hiệu di tích quốc gia":"92-VHTT\/QĐ<ref>{{chú thích web|title={{ucfirst:{{lc:QUYẾT ĐỊNH CỦA BỘ VĂN HOÁ SỐ 92 - VHTT\/QĐ NGÀY 10 THÁNG 7 NĂM 1980 XẾP HẠNG 17 DI TÍCH LỊCH SỬ VÀ VĂN HOÁ}}}} |url=https:\/\/m.thuvienphapluat.vn\/van-ban\/Tai-nguyen-Moi-truong\/Quyet-dinh-92-VHTT-QD-xep-hang-17-di-tich-lich-su-van-hoa-44178.aspx|website=Thư viện pháp luật}}","sinh":"","tiền tố":"","lễ hội":"","vĩ độ":"","tên":"Đình So","ngày nhận danh hiệu di tích đặc biệt":"24 tháng 12 năm 2018","loại di tích đặc biệt":"Kiến trúc nghệ thuật","người sáng lập":"","quyết định danh hiệu di tích đặc biệt":"1820\/QĐ-TTg<ref>{{chú thích web|title=Quyết định số 1820\/QĐ-TTg của Thủ tướng Chính phủ: Về việc xếp hạng di tích quốc gia đặc biệt|url=http:\/\/vanban.chinhphu.vn\/portal\/page\/portal\/chinhphu\/hethongvanban?class_id=2&_page=1&mode=detail&document_id=195676|website=Cổng thông tin điện tử Chính phủ nước Cộng hòa xã hội chủ nghĩa Việt Nam}}<\/ref>"}},"Đền Kim Liên":{"154444":{"tên khác":"Đình Kim Liên, Kim Liên từ, đền Cao Sơn","chú thích":"Cổng trong Đền Kim Liên, ba chữ Nho trên trước cổng là \"Trấn Nam phương\"","hình":"Kim Lien shrine.jpg","tên thánh":"[[Thần Cao Sơn#Thần Cao Sơn ở Ninh Bình|Cao Sơn]]","đóng cửa":"","công trạng":"","nguyên nhân đóng cửa":"","kinh độ":"","mất":"","xây mới":"","xây dựng":"1509","địa chỉ":"148 phố [[Kim Hoa]], phường [[Phương Liên]], quận [[Đống Đa]], thành phố [[Hà Nội]]","tên di tích đặc biệt":"Thăng Long tứ trấn","tôn tạo":"","một phần của di tích (đặc biệt)":"Thăng Long tứ trấn","sinh":"","tiền tố":"Đại vương","lễ hội":"16 tháng 3 âm lịch","vĩ độ":"","tên":"Đền Kim Liên","ngày nhận danh hiệu di tích đặc biệt":"18 tháng 1 năm 2022","loại di tích đặc biệt":"Lịch sử - văn hóa","người sáng lập":"[[Lê Tương Dực]]","quyết định danh hiệu di tích đặc biệt":"93\/QĐ-TTg<ref>{{Chú thích web|url=http:\/\/dsvh.gov.vn\/quyet-dinh-xep-hang-di-tich-quoc-gia-dac-biet-dot-12-3450|tựa đề=Quyết định xếp hạng di tích quốc gia đặc biệt (đợt 12)|tác giả=Đức Dũng|website=Cục di sản văn hóa|url-status=live}}<\/ref> }}","loại di tích đặc biệt 2":"Kiến trúc nghệ thuật"}},"Đình Trung Cần":{"818467":{"quyết định danh hiệu di tích quốc gia":"51-VH\/QĐ }}","loại di tích quốc gia":"Kiến trúc nghệ thuật","tên":"Đình Trung Cần","ngày nhận danh hiệu di tích quốc gia":"12 tháng 01 năm 1996","xây dựng":"1781","hình":"Đình Trung Cần.jpg","tên thánh":"Tống Tất Thắng"}},"Đền Bà Triệu":{"474451":{"ngày nhận":"[[31 tháng 12]] năm [[2014]]","bản đồ 1":"","tên khác":"","chú thích":"Tam quan Đền Bà Triệu","hình":"Den-tho-ba-trieu.jpg","tên thánh":"[[Bà Triệu|Triệu Thị Trinh]]","điện thoại":"","đóng cửa":"","công trạng":"Đánh đuổi quân xâm lược [[Đông Ngô]]","di tích":"[[Di tích quốc gia đặc biệt|Di tích Quốc gia Đặc biệt]]","kinh độ":"105.8195","web":"","tên di tích":"Khu Di tích Bà Triệu","mất":"[[248]]","xây mới":"","ghi chú bản đồ 1":"","địa chỉ":"thôn Phú Điền, xã [[Triệu Lộc]], huyện [[Hậu Lộc]], tỉnh [[Thanh Hóa]]","tôn tạo":"","sinh":"[[226]]","loại đền":"","thành lập":"","lễ hội":"21-24 tháng 2 [[âm lịch]]","thánh tích":"","tước vị":"","cấp di tích":"đặc biệt","vĩ độ":"19.9293","quyết định":"2408\/QĐ-TTg<ref>{{Chú thích web|url=https:\/\/thuvienphapluat.vn\/van-ban\/Van-hoa-Xa-hoi\/Quyet-dinh-2408-QD-TTg-2014-xep-hang-di-tich-quoc-gia-dac-biet-2014-311757.aspx|title=Quyết định 2408\/QĐ-TTg 2014 xếp hạng di tích quốc gia đặc biệt 2014}}<\/ref> }}","loại di tích 3":"nghệ thuật","đối tượng thờ":"Anh hùng Dân tộc","loại di tích 2":"kiến trúc","tên":"Đền Bà Triệu","người sáng lập":"","loại di tích":"lịch sử"}},"Đền Nội Bình Đà":{"3705304":{"ngày nhận danh hiệu di tích cấp quốc gia":"1991 }}","tiền tố":"Lạc Long Quân","tên":"Đền Nội Bình Đà","thánh tích":"Thủy tổ trong truyền thuyết của người Việt","hình":"Đền Nội Bình Đà,.jpg","tên thánh":"[[Lạc Long Quân|Sùng Lãm]]","địa chỉ":"làng Bình Đà, xã Bình Minh, huyện Thanh Oai, [[Hà Nội]]"}},"Đền Cao An Phụ":{"19709308":{"tên khác":"An Phụ Sơn Từ","tên di tích đặc biệt":"Quần thể An Phụ \u2013 Kính Chủ \u2013 Nhẫm Dương","sinh":"1211","tên di tích quốc gia":"Đền Cao An Phụ","tiền tố":"An Sinh Vương","loại di tích quốc gia 2":"Thắng cảnh }}","tên thánh":"[[Trần Liễu]]","vĩ độ":"21.014192","kinh độ":"106.492662","loại di tích quốc gia":"Lịch sử - văn hóa","mất":"1251","tên":"Đền Cao An Phụ","ngày nhận danh hiệu di tích đặc biệt":"22 tháng 12, 2016","ngày nhận danh hiệu di tích quốc gia":"1992","xây dựng":"1251","loại di tích đặc biệt":"Lịch sử - văn hóa","địa chỉ":"núi An Phụ, phường [[An Sinh]], thị xã [[Kinh Môn]], tỉnh [[Hải Dương]]","được thờ vì":"Hoàng tử [[nhà Trần]]","loại di tích đặc biệt 2":"Thắng cảnh"}},"Đền Bách Linh":{"14843454":{"sinh":"924","tiền tố":"Đinh Tiên Hoàng","mất":"979","tên":"Đền Bách Linh","hình":"Đền Bách Linh.jpg","tên thánh":"[[Đinh Bộ Lĩnh]]","địa chỉ":"thôn Dư Xá Thượng, xã [[Hòa Nam, Ứng Hòa|Hòa Nam]], huyện [[Ứng Hòa]], [[Hà Nội]] }}","được thờ vì":"Hoàng đế [[nhà Đinh]]"}},"Đền Dầm":{"2415287":{"tôn giáo":"[[Đạo Mẫu]]","tiền tố":"Thủy cung Thánh Mẫu","lễ hội":"1 - 10 tháng 2 âm lịch<br>({{Âm lịch|A2D|D=1|M=2|Y={{CURRENTISOYEAR}}|df=dM}} - {{Âm lịch|A2D|D=10|M=2|Y={{CURRENTISOYEAR}}|df=jMY}}) }}","tên":"Đền Dầm","tên thánh":"[[Mẫu Thoải]]","địa chỉ":"thôn Xâm Dương, xã [[Ninh Sở]], huyện [[Thường Tín]], [[Hà Nội]]"}},"Bảo tàng Đồng Nai":{"19735016":{"image":"Binh Da Lithophone.jpg","image_size":"180px","chất liệu":"[[Đá phiến]]","khối lượng":"","caption":"Một phần bộ sưu tập đàn đá Bình Đa","kích thước":"","image2":"","chiều rộng":"","thời điểm phát hiện":"1979","chiều cao":"","nơi lưu trữ":"Bảo tàng Đồng Nai","địa điểm phát hiện":"Di chỉ Bình Đa<br>[[An Bình, Biên Hòa]]<ref name=\"Nguyễn Hồng Ân 2\">{{Chú thích báo|tác giả=Nguyễn Hồng Ân |url=http:\/\/www.baodongnai.com.vn\/dong-nai-cuoi-tuan\/202302\/dan-da-binh-da-sang-tao-nghe-thuat-ban-dia-dac-sac-3155711\/ |tên bài=Đàn đá Bình Đa - sáng tạo nghệ thuật bản địa đặc sắc |nhà xuất bản=Báo Đồng Nai điện tử |năm=2023 |ngày truy cập=14 tháng 2 năm 2023 | url lưu trữ=| ngày lưu trữ=}}<\/ref>","tiêu đề phụ":"''[[Bảo vật quốc gia (Việt Nam)#Đợt 11|Bảo vật quốc gia]] số 6, đợt 11''","name":"Sưu tập đàn đá Bình Đa","image2_size":"","số đăng ký":"}}","niên đại":"cách nay 3000","phát hiện bởi":"","thời kỳ\/văn hóa":"[[Văn hóa Óc Eo]]"}},"Đình Long Thanh":{"824683":{"ngày nhận":"{{startdate|1991|03|25}}","tên khác":"Long Thanh miếu vũ","hình":"Đình Tân Thanh.jpg","tên thánh":"","đóng cửa":"","công trạng":"","nguyên nhân đóng cửa":"","kinh độ":"","tên di tích":"","mất":"","xây mới":"1844","xây dựng":"1754","địa chỉ":"phường 5, Vĩnh Long, [[Vĩnh Long]]","tôn tạo":"","sinh":"","tiền tố":"","lễ hội":"","cấp di tích":"quốc gia","vĩ độ":"","quyết định":"}}","loại di tích 3":"","loại di tích 2":"văn hóa","tên":"Đình Long Thanh","người sáng lập":"","loại di tích":"lịch sử"}},"Đền Bia":{"19567681":{"tên di tích đặc biệt":"Đền Xưa - Chùa Giám - Đền Bia","một phần của di tích (đặc biệt)":"cụm di tích [[Đền Xưa]] - [[Chùa Giám]] - Đền Bia","sinh":"1330","tiền tố":"Danh y, Thiền sư","tên thánh":"[[Tuệ Tĩnh]]","cấp di tích":"đặc biệt }}","vĩ độ":"20.977854","kinh độ":"106.253361","mất":"1400","tên":"Đền Bia","ngày nhận danh hiệu di tích đặc biệt":"25\/12\/2017","xây mới":"1936","xây dựng":"thời Lê","loại di tích đặc biệt":"lịch sử","địa chỉ":"xã Cẩm Văn, huyện Cẩm Giàng, tỉnh Hải Dương","quyết định danh hiệu di tích đặc biệt":"2082\/QĐ-TTg"}},"Phủ Tây Hồ":{"46770":{"ngày nhận":"{{startdate|1996|2|12}}","tôn tạo":"","sinh":"","tiền tố":"Công chúa","lễ hội":"3 tháng 3 và 13 tháng 8 âm lịch","hình":"Phủ Tây Hồ.jpg","tên thánh":"[[Liễu Hạnh công chúa|Liễu Hạnh]]","đóng cửa":"","công trạng":"","nguyên nhân đóng cửa":"","cấp di tích":"quốc gia","vĩ độ":"","kinh độ":"","quyết định":"}}","loại di tích 3":"","tên di tích":"","loại di tích 2":"văn hóa","mất":"","tên":"Phủ Tây Hồ","xây mới":"","xây dựng":"","người sáng lập":"","địa chỉ":"52 phố [[Đặng Thai Mai]], phường [[Quảng An, Tây Hồ|Quảng An]], [[Tây Hồ (quận)|Tây Hồ]], thành phố [[Hà Nội]]","loại di tích":"lịch sử"}},"Đền thờ Trương Định":{"19803466":{"quyết định danh hiệu di tích quốc gia":"400\/QÐ-BVHTTDL }}","sinh":"1820","tên di tích quốc gia":"Đền thờ","loại di tích quốc gia":"Di tích lịch sử","tiền tố":"","mất":"1864","tên":"Đền thờ Trương Định","ngày nhận danh hiệu di tích quốc gia":"[[24 tháng 2]] năm [[2023]]","loại di tích quốc gia 2":"","hình":"","tên thánh":"Trương Định","địa chỉ":"Xóm Khê Thuận, xã Tịnh Khê, TP. [[Quảng Ngãi (thành phố)|Quảng Ngãi]]"}},"Tượng Quan Âm nghìn mắt nghìn tay (chùa Bút Tháp)":{"19586788":{"image":"La statue de Quan Am dans la pagode But Thap.jpg","image_size":"200px","chất liệu":"[[Gỗ mít]]","caption":"Tượng Phật bà Quan Âm nghìn mắt nghìn tay","chiều rộng":"210 cm","chiều dày":"115 cm","chiều cao":"365 cm","nơi lưu trữ":"Chùa Bút Tháp }}","tiêu đề phụ":"''[[Bảo vật quốc gia (Việt Nam)#Đợt 1|Bảo vật quốc gia]] số 23, đợt 1''","name":"Tượng Phật bà Quan Âm nghìn mắt nghìn tay<br>''Thiên thủ thiên nhãn Quan thế âm Bồ tát Phật tượng''","niên đại":"1656","hệ chữ viết":"[[Chữ Hán]]","thời kỳ\/văn hóa":"[[Lê Trung Hưng]]"}},"Đền Cuông":{"417515":{"tên khác":"Đền Công","quyết định danh hiệu di tích quốc gia":"09\/QĐ-VH<ref>{{Chú thích web|url=https:\/\/thuvienphapluat.vn\/van-ban\/Van-hoa-Xa-hoi\/Quyet-dinh-09-VH-QD-xep-hang-di-tich-lich-su-van-hoa-dot-IV-44672.aspx|tựa đề=Quyết định 09-VH\/QĐ xếp hạng di tích lịch sử văn hoá đợt IV|website=thuvienphapluat.vn|ngày truy cập=2023-01-07}}<\/ref> }}","sinh":"?","tên di tích quốc gia":"Đền Cuông","tiền tố":"An Dương Vương","lễ hội":"14,15,16 tháng 2 Âm lịch","hình":"Đền Cuông 8, Diễn An, Diễn Châu, Nghệ An.jpeg","tên thánh":"[[Thục Phán]]","loại di tích quốc gia":"Lịch sử - văn hóa","mất":"179 TCN","tên":"Đền Cuông","ngày nhận danh hiệu di tích quốc gia":"21-2-1975","địa chỉ":"núi Mộ Dạ thuộc xã Diễn An, huyện Diễn Châu, tỉnh Nghệ An"}},"Đình Ba Dân":{"546406":{"sinh":"919","tiền tố":"Chiêu Nghĩa đại vương","mất":"967","lễ hội":"14-16 tháng 2 Âm lịch }}","tên":"Đình Ba Dân","hình":"Dinhbadank3.JPG","tên thánh":"[[Nguyễn Bồ]]","địa chỉ":"xã [[Tứ Hiệp]], huyện [[Thanh Trì]], [[Hà Nội]]","công trạng":"Khai quốc công thần [[nhà Đinh]]"}},"Đình_Chu_Quyến":{"565184":{"ngày nhận":"28 tháng 4 năm 1962","chú thích":"Đình Chu Quyến","hình":"Đình Tràng.JPG","tên thánh":"[[Nhã Lang Vương|Nhã Lang]]","điện thoại":"","đóng cửa":"","công trạng":"","tiêu chuẩn":"","kinh độ":"105.442898","web":"","tên di tích":"Đình Chu Quyến","mất":"","xây mới":"","loại":"đình","địa chỉ":"","tôn tạo":"","một phần của":"}}","sinh":"","loại đền":"","thành lập":"[[thế kỷ 17]]","lễ hội":"","thánh tích":"","hồ sơ tham khảo":"","tước vị":"Nhã Lang vương","cấp di tích":"quốc gia","vĩ độ":"21.196232","quyết định":"313-VH\/VP<ref>{{Chú thích web|url=https:\/\/thuvienphapluat.vn\/van-ban\/Van-hoa-Xa-hoi\/Quyet-dinh-313-VH-VP-xep-hang-nhung-di-tich-danh-thang-canh-toan-mien-Bac-19864.aspx|title=Quyết định 313-VH\/VP xếp hạng những di tích, danh thắng cảnh toàn miền Bắc|website=Thư viện pháp luật}}<\/ref>","loại di tích 3":"","đối tượng thờ":"nhân vật lịch sử","loại di tích 2":"văn hóa","tên":"Đình Chu Quyến","người sáng lập":"","loại di tích":"lịch sử"}},"Đền Nhà Bà":{"253724":{"ngày nhận":"2009","tên khác":"Đền Vại","hình":"","tên thánh":"","đóng cửa":"","công trạng":"","nguyên nhân đóng cửa":"","danh sách":"#Thờ tự","kinh độ":"","tên di tích":"Đền Vại","mất":"","xây mới":"","xây dựng":"","địa chỉ":"","tôn tạo":"","sinh":"","tiền tố":"","lễ hội":"12 tháng 2 âm lịch","cấp di tích":"tỉnh","vĩ độ":"","quyết định":"}}","loại di tích 3":"","loại di tích 2":"văn hóa","thờ phụng":"Nhiều vị","tên":"Đền Nhà Bà","người sáng lập":"","loại di tích":"lịch sử"}}}