{"1242687":{"Thông tin đơn vị hành chính Việt Nam\n":[{"diện tích":"12,61 km²<ref name=MS\/>","vĩ giây":"30","vùng":"[[Duyên hải Nam Trung Bộ]]","dân số":"11408 người<ref name=MS\/>","thành lập":"","tỉnh":"[[Quảng Ngãi]]","huyện":"[[Bình Sơn]]","trụ sở UBND":"","kinh phút":"44","mật độ dân số":"905 người\/km²","hình":"","kinh giây":"35","vĩ độ":"15","kinh độ":"108","thời điểm dân số":"1999","dân tộc":"","vai trò hành chính":"Xã","mã hành chính":"21052<ref>[https:\/\/danhmuchanhchinh.gso.gov.vn\/ Tổng cục Thống kê]<\/ref>","tên":"Bình Chánh","vĩ phút":"21","mã bưu chính":"}}","ghi chú hình":""}]}}