{"56337":{"Thông tin đơn vị hành chính Việt Nam ":[{"bản đồ 1":"{{maplink|frame=yes|plain=yes|type=shape|frame-width=280|frame-align=center|stroke-width=3}}","diện tích":"377,5&nbsp;km²","dân số thành thị":"","vùng":"[[Đông Nam Bộ]]","hình":"Tuongdaichienthang_.jp.jpg","dân số nông thôn":"","kinh giây":"54","biển số xe":"93-G1","kinh độ":"106","thời điểm dân số":"2020","web":"{{url|budop.binhphuoc.gov.vn}} }}","dân tộc":"","mã hành chính":"693<ref>[https:\/\/danhmuchanhchinh.gso.gov.vn\/ Tổng cục Thống kê]<\/ref>","vĩ phút":"59","mã bưu chính":"","huyện lỵ":"thị trấn [[Thanh Bình, Bù Đốp|Thanh Bình]]","vĩ giây":"08","dân số":"55,131 người","thành lập":"2003: tái lập<ref name=ND17 \/>","tỉnh":"[[Bình Phước]]","trụ sở UBND":"","kinh phút":"49","mật độ dân số":"137 người\/km","bí thư":"","vĩ độ":"11","chủ tịch HĐND":"","tên":"Bù Đốp","chủ tịch UBND":"","phân chia hành chính":"1 thị trấn, 6 xã","ghi chú hình":"Tượng đài chiến thắng Bù Đốp"}]}}