{"1489470":{"coord":[{"{{coord|10.7333783|106.7179385|format":"dms|display=inline,title}}"}],"Thông tin bệnh viện\n":[{"pushpin_map":"TPHCM","funding":"lợi nhuận","website":"{{website|https:\/\/tamduchearthospital.com\/}} }}","khai trương":"{{Ngày bắt đầu và tuổi|2006|03|08}}<ref name=\":0\"\/>","thành lập":"2004<ref name=\":0\">{{Chú thích web|url=https:\/\/tamduchearthospital.com\/gioi-thieu\/lich-su\/|tựa đề=Lịch sử|url-status=live}}<\/ref>","coordinates":"{{coord|10.7333783|106.7179385|format=dms|display=inline,title}}","giường":"370<ref name=\":0\"\/>","hình":"Bệnh viện Tâm Đức.JPG","điện thoại":"(+84-28) 54 110 036 <br \/> (+84) 903 052 432","thành phố":"[[Thành phố Hồ Chí Minh]]","tên":"Bệnh viện Tâm Đức","tổ chức":"Công ty Cổ phần Bệnh viện Tim Tâm Đức","loại":"Chuyên khoa Tim mạch","quốc gia":"{{VNM}}","vị trí":"Khu A Phú Mỹ Hưng, đại lộ Nam Sài Gòn, Tân Phú, [[Quận 7]]"}],"Cần biên tập":[{"{{Cần biên tập|date":"tháng 11\/2021}}"}],"Ngày bắt đầu và tuổi":[{}]}}