{"1243209":{"Thông tin đơn vị hành chính Việt Nam ":[{"diện tích":"75,76 km²<ref name=XCX\/>","vĩ giây":"4","vùng":"[[Tây Bắc Bộ]]","dân số":"3.210 người<ref name=XCX\/>","thành lập":"8\/1\/2007<ref name=03\/2007\/NĐ-CP\/>","tỉnh":"[[Sơn La]]","huyện":"[[Vân Hồ]]","trụ sở UBND":"","kinh phút":"40","mật độ dân số":"42 người\/km²","hình":"","kinh giây":"38","vĩ độ":"20","kinh độ":"104","thời điểm dân số":"2020","mã hành chính":"04056<ref>[https:\/\/danhmuchanhchinh.gso.gov.vn\/ Tổng cục Thống kê]<\/ref>","tên":"Chiềng Xuân","vĩ phút":"44","mã bưu chính":"}}","ghi chú hình":""}]}}