{"1759846":{"Thông tin chùa\n":[{"country":"{{flagicon|Vietnam}} Việt Nam","abbot":"[[Trần Thái Tông]]","img":"","website":"http:\/\/www.phattuvietnam.net }}","address":"Phường [[Tân Thành, thành phố Ninh Bình|Tân Thành]],<br> [[ninh Bình (thành phố)|thành phố Ninh Bình]], tỉnh [[Ninh Bình]]","director":"[[Giáo hội Phật giáo Việt Nam]]","founder":"Vua [[Lê Đại Hành]]","founded":"Năm [[984]] (năm Thiên Phúc thứ 5)<br>Dựng lại [[1944]]<br>Trùng tu [[1992]]","priest":"","img_size":"300","roshi":"","rinpoche":"","denomination":"Phật giáo Đại thừa","img_capt":"Tam quan chùa","reverend":"","teacher":"","name":"Chùa Đẩu Long<br>","closed":""}],"flagicon":[{}]}}