{"1243230":{"Thông tin đơn vị hành chính Việt Nam\n":[{"diện tích":"133,59 km²<ref name=MS\/>","vĩ giây":"13","vùng":"[[Tây Nguyên]]","dân số":"10.684 người<ref name=MS\/>","thành lập":"2002<ref>54\/2002\/NĐ-CP<\/ref>","tỉnh":"[[Gia Lai]]","huyện":"[[Phú Thiện]]","trụ sở UBND":"","kinh phút":"17","mật độ dân số":"80 người\/km²","hình":"","kinh giây":"43","vĩ độ":"13","kinh độ":"108","thời điểm dân số":"2002","vai trò hành chính":"Xã","mã hành chính":"24046<ref>[https:\/\/danhmuchanhchinh.gso.gov.vn\/ Tổng cục Thống kê]<\/ref>","tên":"Chư A Thai","vĩ phút":"36","mã bưu chính":"}}","ghi chú hình":""}]}}