{"145248":{"commons cat":[{}],"Thông tin đơn vị hành chính Việt Nam ":[{"bản đồ 1":"{{maplink|frame=yes|plain=yes|type=shape|frame-width=280|frame-align=center|stroke-width=3}}","diện tích":"425,03 km²","dân số thành thị":"","vùng":"[[Bắc Trung Bộ]]","hình":"Suoi ca Cam Luong.jpg","dân số nông thôn":"","kinh giây":"11","biển số xe":"36-L1}}","kinh độ":"105","thời điểm dân số":"2009","web":"{{url|camthuy.thanhhoa.gov.vn}}","dân tộc":"[[Mường]], [[Người Việt|Kinh]], [[Người Dao|Dao]],...","mã hành chính":"390<ref>[https:\/\/danhmuchanhchinh.gso.gov.vn\/ Tổng cục Thống kê]<\/ref>","vĩ phút":"11","mã bưu chính":"","huyện lỵ":"Thị trấn [[Phong Sơn (thị trấn)|Phong Sơn]]","vĩ giây":"14","dân số":"113.580 người","thành lập":"1954","tỉnh":"[[Thanh Hóa]]","trụ sở UBND":"Thị trấn [[Phong Sơn (thị trấn)|Phong Sơn]]","kinh phút":"28","mật độ dân số":"267 người\/km²","bí thư":"","vĩ độ":"20","chủ tịch HĐND":"","tên":"Cẩm Thủy","chủ tịch UBND":"","phân chia hành chính":"1 thị trấn, 16 xã","ghi chú hình":"[[Suối Cá thần]] tại chân núi Trường Sinh, thuộc bản Ngọc, xã Cẩm Lương"}]}}