{"19775448":{"Ngày sinh và tuổi":[{}],"Thông tin nghệ sĩ\n":[{"năm hoạt động điện ảnh":"1978 - 2020","con":"2","quốc tịch":"{{VNM}}","tiền tố":"Nghệ sĩ Ưu tú","phim":"Ngày ấy bên sông Lam","giải thưởng điện ảnh":"[[Giải Bông Sen cho nữ diễn viên chính xuất sắc]] (1983) }}","hình":"","đào tạo điện ảnh":"[[Trường Điện ảnh Việt Nam]]","nghề nghiệp":"Diễn viên","chồng":"[[Phạm Quang Vĩnh]]","danh hiệu":"Nghệ sĩ Ưu tú","nơi sinh":"[[Cát Hải]], [[Cát Bà]], [[Hải Phòng]]","studio điện ảnh":"[[Hãng Phim truyện Việt Nam]]","tên":"Diệu Thuần","ngày sinh":"{{Ngày sinh và tuổi|1957|7|5}}","chú thích hình":"Nghệ sĩ Diệu Thuần trong phim thập niên 90","vai diễn":"Thúy","nền":"Diễn viên"}]}}