{"1243602":{"Thông tin đơn vị hành chính Việt Nam\n":[{"diện tích":"6,31 km²<ref name=MS\/>","vĩ giây":"59","vùng":"[[Đông Bắc Bộ]]","dân số":"9.835 người<ref name=MS\/>","thành lập":"1958<ref name=145-NV\/>","tỉnh":"[[Bắc Giang]]","trụ sở UBND":"","kinh phút":"14","mật độ dân số":"1.427 người\/km²","hình":"","kinh giây":"13","thành phố":"[[Bắc Giang (thành phố)|Bắc Giang]]","vĩ độ":"21","kinh độ":"106","thời điểm dân số":"2010","dân tộc":"Kinh","vai trò hành chính":"Xã","mã hành chính":"07441<ref>[https:\/\/danhmuchanhchinh.gso.gov.vn\/ Tổng cục Thống kê]<\/ref>","tên":"Dĩnh Trì","vĩ phút":"16","mã bưu chính":"}}","ghi chú hình":""}]}}