{"95463":{"Thông tin đơn vị hành chính Việt Nam ":[{"bản đồ 1":"{{maplink|frame=yes|plain=yes|type=shape|frame-width=280|frame-align=center|stroke-width=3}}","diện tích":"1.039,57 km²","dân số thành thị":"28.674 người (18%)","vùng":"[[Đồng bằng sông Cửu Long]]","hình":"Khu mộ Chị Sứ.jpg","điện thoại":"02973","dân số nông thôn":"128.096 người (82%)","biển số xe":"68-D1","kinh độ":"104.927222","thời điểm dân số":"2020","web":"{{url|hondat.kiengiang.gov.vn}} }}","dân tộc":"[[Người Khmer|Khmer]], [[Người Hoa|Hoa]], [[Người Việt|Kinh]]","mã hành chính":"903<ref>[https:\/\/danhmuchanhchinh.gso.gov.vn\/ Tổng cục Thống kê]<\/ref>","mã bưu chính":"","fax":"","huyện lỵ":"Thị trấn [[Hòn Đất (thị trấn)|Hòn Đất]]","dân số":"156.770 người<ref name=KIENGIANG2020\/>","thành lập":"1978","tỉnh":"[[Kiên Giang]]","trụ sở UBND":"61 Quốc lộ 80, thị trấn Hòn Đất","mật độ dân số":"151 người\/km²","bí thư":"Trương Văn Minh","vĩ độ":"10.187404","tên":"Hòn Đất","phân chia hành chính":"2 thị trấn, 12 xã","chủ tịch UBND":"Dương Minh Tâm","ghi chú hình":"Khu di tích lịch sử mộ Chị Sứ ở xã Thổ Sơn"}]}}