{"244634":{"Thông tin đơn vị hành chính Việt Nam\n":[{"diện tích":"5,72 km²<ref name=MS\/>","vĩ giây":"31","vùng":"[[Đồng bằng sông Hồng]]","dân số":"8.355 người<ref name=MS\/>","thành lập":"2007<ref name=\"145\/2007\/NĐ-CP\"\/>","trụ sở UBND":"","kinh phút":"44","mật độ dân số":"1.461 người\/km²","hình":"","kinh giây":"19","thành phố":"[[Hải Phòng]]","vĩ độ":"20","kinh độ":"106","thời điểm dân số":"01\/04\/2019","dân tộc":"","vai trò hành chính":"Phường","mã hành chính":"11737<ref>[https:\/\/danhmuchanhchinh.gso.gov.vn\/ Tổng cục Thống kê]<\/ref>","tên":"Hợp Đức","vĩ phút":"44","mã bưu chính":"}}","ghi chú hình":"","quận":"[[Đồ Sơn]]"}]}}