{"1249996":{"Thông tin đơn vị hành chính Việt Nam":[{"diện tích":"4,83 km²<ref name=MS\/>","vĩ giây":"22","vùng":"[[Duyên hải Nam Trung Bộ]]","dân số":"11.800 người<ref name=MS\/>","thành lập":"","tỉnh":"[[Quảng Ngãi]]","huyện":"[[Tư Nghĩa]]","trụ sở UBND":"","kinh phút":"49","mật độ dân số":"2.443 người\/km²","hình":"","kinh giây":"30","vĩ độ":"15","kinh độ":"108","thời điểm dân số":"2017","dân tộc":"Kinh...","mã hành chính":"21235<ref>[https:\/\/danhmuchanhchinh.gso.gov.vn\/ Tổng cục Thống kê]<\/ref>","tên":"La Hà","vĩ phút":"5","mã bưu chính":"}}","ghi chú hình":""}]}}