{"2455296":{"Infobox Korean name":[{"{{Infobox Korean name|hangul":"이근호|hanja=李根鎬|rr=Yi Geun-ho|mr=Yi Kŭn-ho}}"}],"birth date and age":[{"{{birth date and age|1985|4|11|df":"yes}}"}],"Navboxes colour\n":[{"list1":"{{Đội hình Hàn Quốc tại Cúp bóng đá châu Á 2007}} {{Đội hình bóng đá nam Hàn Quốc tại Thế vận hội Mùa hè 2008}} {{Đội hình Hàn Quốc tại Giải bóng đá vô địch thế giới 2014}} {{Đội hình Hàn Quốc tại Cúp bóng đá châu Á 2015}} }}","fg":"white","bg":"#C21E2B","title":"Đội hình Hàn Quốc","bordercolor":"#0047A0"}],"height":[{"{{height|m":"1,76}}"}]}}