{"3210502":{"ngày mất và tuổi":[{}],"ngày sinh":[{}],"thời gian sống":[{}],"Thông tin viên chức\n":[{"phục vụ":"","đảng":"[[Đảng Cộng sản Việt Nam]]","phó viên chức":"","quốc tịch":"{{VIE}}","phó chức vụ":"","hình":"","nơi mất":"[[Thành phố Hồ Chí Minh]], [[Việt Nam]]","quê quán":"[[Nghệ An]], [[Hà Nội]], [[Tây Ninh (thành phố)|Tây Ninh]]","khen thưởng":"}}","ngày mất":"{{ngày mất và tuổi|2022|03|26|1927|5|1}}","chức vụ":"","nguyên nhân mất":"","đơn vị":"","nơi sinh":"[[Quỳnh Hoa, Quỳnh Lưu]]<br>[[Nghệ An]], [[Liên bang Đông Dương]]","nơi ở":"[[Sài Gòn]]","bắt đầu":"","tên":"Lê Nam Phong","ngày sinh":"{{ngày sinh|1927|5|19}}","kế nhiệm":"","kết thúc":"","họ hàng":"","cấp bậc":"","tiền nhiệm":""}]}}