{"19721878":{"thời gian sống":[{"{{thời gian sống|sinh":"1914|mất=1941}}"}],"Viên chức\n":[{"con":"","miêu tả":"","đảng":"[[Đảng Cộng sản Việt Nam]]","chú thích":"}}","chức vụ 2":"","phó chức vụ":"","hình":"","tiền nhiệm 2":"","kế nhiệm 2":"","chữ ký":"","phó chức vụ 2":"","chồng":"","cỡ hình":"","dân tộc":"[[Người Kinh|Kinh]]","học trường":"","nơi ở":"","giáo dục":"","cha":"","đa số":"","địa hạt 2":"","nghề":"","website":"","phó viên chức":"","ngày chết":"16 tháng 6, 1941","mẹ":"","nơi chết":"","vợ":"","bắt đầu 2":"","phó viên chức 2":"","chức vụ":"Bí thư [[Thành ủy Thành phố Hồ Chí Minh|Tỉnh ủy Gia Định]]","nơi sinh":"Hóc Môn, Gia Định","địa hạt":"{{VIE}}","đạo":"","bắt đầu":"Tháng 7, 1940","học vị":"","tên":"Mười Đen","ngày sinh":"[[1914]]","kế nhiệm":"[[Bùi Văn Châu]]","kết thúc":"Tháng 5, [[1941]]","họ hàng":"","kết hợp dân sự":"","kết thúc 2":"","tiền nhiệm":"[[Bùi Văn Ngữ]]"}]}}