{"3690393":{"Thông tin nhân vật phong kiến\n":[{"tước hiệu":"","tên khác":"Trương Bá Ngọc 張伯玉","chức quan":"[[Thái sư]]<!-- chức cao nhất -->","hình":"","tôn xưng":"","nơi mất":"","chồng":"","cỡ hình":"","bút danh":"","dân tộc":"","mất":"[[1130]]","cha":"","quốc gia":"[[Đại Việt]]","học vấn":"<!-- tiến sĩ, cử nhân -->","phối ngẫu 2":"","tôn giáo":"","sinh":"","húy":"","nơi an táng":"","quốc tịch":"","phối ngẫu":"","tác phẩm":"<!-- nổi bật --> }}","kiểu phối ngẫu 2":"","tước vị":"[[Hầu tước]]","mẹ":"","vợ":"","ngày an táng":"","nghề nghiệp":"","triều đại":"[[Nhà Lý]]<!-- triều đại mà nhân vật sống, nếu nhân vật sống qua nhiều triều đại, ngăn cách bằng dấu phẩy -->","giới tính":"[[Nam giới|Nam]]","tên gốc":"黎伯玉","kiểu phối ngẫu":"<!-- thê, thiếp, phu quân -->","nơi sinh":"","tên":"Lê Bá Ngọc","hiệu":"","con cái":"<!-- ngăn cách bằng <br> -->","ghi chú hình":"","tự":""}],"refbegin":[{}],"thời gian sống":[{"{{thời gian sống|sinh":"|mất=1130}}"}],"linktext":[{}]}}