{"1250019":{"Thông tin đơn vị hành chính Việt Nam\n":[{"bản đồ 1":"{{maplink|frame=yes|plain=yes|type=shape|frame-width=280|frame-align=center|stroke-width=3}}","diện tích":"0,72 km²<ref name=MS\/>","vĩ giây":"50","vùng":"[[Đồng bằng sông Hồng]]","dân số":"8.379 người<ref name=MS\/>","thành lập":"1987<ref>38\/1987\/QĐ-HĐBT<\/ref>","trụ sở UBND":"","kinh phút":"41","mật độ dân số":"11.638 người\/km²","hình":"Ủy ban phường Lạch Tray.JPG","kinh giây":"22","thành phố":"[[Hải Phòng]]","vĩ độ":"20","kinh độ":"106","thời điểm dân số":"01\/04\/2019","dân tộc":"","vai trò hành chính":"phường","mã hành chính":"11362<ref>[https:\/\/danhmuchanhchinh.gso.gov.vn\/ Tổng cục Thống kê]<\/ref>","tên":"Lạch Tray","vĩ phút":"50","mã bưu chính":"}}","ghi chú hình":"Ủy ban nhân dân phường Lạch Tray","quận":"[[Ngô Quyền (quận)|Ngô Quyền]]"}]}}