{"1250646":{"Thông tin đơn vị hành chính Việt Nam\n":[{"diện tích":"187,36 km²<ref name=MS\/>","vĩ giây":"56","vùng":"[[Tây Bắc Bộ]]","dân số":"6642 người<ref name=MS\/>","thành lập":"1975<ref>11\/1975\/QĐ-BT<\/ref>","tỉnh":"[[Sơn La]]","huyện":"[[Quỳnh Nhai]]","trụ sở UBND":"","kinh phút":"43","mật độ dân số":"35 người\/km²","hình":"","kinh giây":"16","vĩ độ":"21","kinh độ":"103","thời điểm dân số":"1999","dân tộc":"","vai trò hành chính":"Xã","mã hành chính":"03694<ref>[https:\/\/danhmuchanhchinh.gso.gov.vn\/ Tổng cục Thống kê]<\/ref>","tên":"Mường Giôn","vĩ phút":"44","mã bưu chính":"}}","ghi chú hình":""}]}}