{"238110":{"Thời gian sống":[{"{{Thời gian sống|sinh":"1917|mất=1992}}"}],"HCVN":[{}],"ngày mất và tuổi":[{}],"ngày sinh":[{}],"Thông tin nghệ sĩ\n":[{"hạng mục 1":"Văn học nghệ thuật }}","quốc tịch":"{{VIE}}","hội nhóm hội họa":"[[Hội Mỹ thuật Việt Nam]]","hình":"NVTy.gif","năm 1":"[[Giải thưởng Hồ Chí Minh đợt II|2000]]","giải thưởng 1":"[[Giải thưởng Hồ Chí Minh]]","nơi mất":"[[Hà Nội]]","khen thưởng":"{{HCVN|Kháng chiến|1|1|Kháng chiến|2|1|Độc lập|3|1}}","đào tạo hội họa":"[[Trường Đại học Mỹ thuật Việt Nam|Cao đẳng Mỹ thuật Đông Dương]]","ngày mất":"{{ngày mất và tuổi|1992|1|19|1917|2|24}}","tác phẩm hội họa":"- ''Nam Bắc một nhà'' (sơn mài, 1961)<br>- ''Cấy ở Tây Bắc'' (lụa)<br>- ''Vịnh Hạ Long'' (sơn mài)","ảnh hưởng tới":"[[Mỹ thuật Việt Nam]] hiện đại","nơi sinh":"[[Hà Nội]]","tên":"Nguyễn Văn Tỵ","ngày sinh":"{{ngày sinh|1917|2|24}}","lĩnh vực hoạt động":"[[Hội họa]]","nền":"họa sĩ"}]}}