{"93746":{"Thông tin nhân vật\n":[{"tên khác":"}}","cỡ chữ ký":"","tên khai sinh":"","giải thưởng":"","cư trú":"","nơi mất":"[[Hà Nội|Đông Kinh]], [[Nhà Lê trung hưng|Việt Nam]]","quê quán":"","chữ ký":"","cỡ hình":"222px","ngày mất":"1654","an táng":"","dân tộc":"","cha":"","học vấn":"","người hôn phối":"[[Mạc Kính Cung|Mạc Đại Tông]]","công việc":"","cân nặng":"","website":"","quốc tịch":"[[Nhà Lê trung hưng|Việt Nam]]","mẹ":"","nhiệm kỳ":"","tác phẩm nổi bật":"","đảng phái":"","tên gốc":"","chiều cao":"","nổi tiếng":"","nơi sinh":"làng Kiệt Đặc, [[Chí Linh|Bằng Châu]], [[Hải Dương|Dương Kinh]], [[Nhà Mạc|Việt Nam]]","tên":"","ngày sinh":"1574","năm hoạt động":"","kế nhiệm":"","tổ chức":"","con cái":"","ghi chú hình":"","tiền nhiệm":""}]}}