{"3375007":{"Thời gian sống":[{}],"Infobox writer\n":[{"occupation":"Nhà văn, giáo sư","signature":"","subject":"","influenced":"","birth_date":"1971","caption":"Nguyễn Thanh Việt vào năm 2015","pseudonym":"","spouse":"","alma_mater":"[[UC Berkeley]]","children":"","notableworks":"''[[The Sympathizer]]'' (2015)<br> ''Nothing Ever Dies: Vietnam and the Memory of War'' (2016)","influences":"","genre":"","image":"Viet Thanh Nguyen - 2015 National Book Festival.JPG","period":"","website":"http:\/\/vietnguyen.info }}","image_size":"","birth_name":"Nguyễn Thanh Việt<ref>{{chú thích web|url=http:\/\/giaitri.vnexpress.net\/tin-tuc\/sach\/lang-van\/nha-van-goc-viet-gianh-giai-pulitzer-van-chuong-3389062.html|title=Nhà văn gốc Việt giành giải Pulitzer văn chương|date=ngày 20 tháng 4 năm 2016|access-date =ngày 20 tháng 4 năm 2016|publisher=VnExpress}}<\/ref>","birth_place":"[[Ban Mê Thuột]], [[Việt Nam Cộng hòa]]","relatives":"","death_date":"","nationality":"{{USA}}","partner":"","awards":"[[Giải Pulitzer cho tác phẩm hư cấu]] (2016)","name":"Nguyễn Thanh Việt","death_place":"","movement":""}]}}