{"555611":{"Thông tin đơn vị hành chính Việt Nam ":[{"diện tích":"4,48","vùng":"[[Bắc Trung Bộ]]","chủ tịch UBMTTQ":"","hình":"","kinh giây":"","kinh độ":"","thời điểm dân số":"","dân tộc":"","mã hành chính":"16042<ref>[https:\/\/danhmuchanhchinh.gso.gov.vn\/ Tổng cục Thống kê]<\/ref>","vĩ phút":"","mã bưu chính":"44332 }}","vị trí lấy tọa độ":"","vĩ giây":"","dân số":"3.973 người (1999)<ref name=QD19\/>; <br>3.444 người (2009)<ref name=\"HL\"\/>","thành lập":"","tỉnh":"[[Thanh Hóa]]","huyện":"[[Hậu Lộc]]","trụ sở UBND":"","kinh phút":"","mật độ dân số":"","thành phố":"","bí thư":"","vĩ độ":"","chủ tịch HĐND":"","tên":"Phong Lộc","chủ tịch UBND":"","ghi chú hình":"","thị xã":""}]}}