{"1251508":{"Thông tin đơn vị hành chính Việt Nam":[{"diện tích":"23,61 km²","vĩ giây":"48","vùng":"[[Đồng bằng sông Cửu Long]]","dân số":"11.572 người","thành lập":"1994<ref name=99\/1994\/NĐ-CP\/>","tỉnh":"[[Trà Vinh]]","huyện":"[[Tiểu Cần]]","trụ sở UBND":"Ấp Đại Mong","kinh phút":"10","mật độ dân số":"490 người\/km²","hình":"","kinh giây":"28","vĩ độ":"9","kinh độ":"106","thời điểm dân số":"2019","mã hành chính":"29347<ref>[https:\/\/danhmuchanhchinh.gso.gov.vn\/ Tổng cục Thống kê]<\/ref>","tên":"Phú Cần","vĩ phút":"48","mã bưu chính":"","ghi chú hình":""}]}}