{"328420":{"Thông tin đơn vị hành chính Việt Nam ":[{"diện tích":"30,45 km²","vĩ giây":"4","vùng":"[[Đông Bắc Bộ]]","dân số":"6.752 người","thành lập":"","tỉnh":"[[Thái Nguyên]]","huyện":"[[Định Hóa]]","trụ sở UBND":"xóm Trung Tâm","kinh phút":"31","mật độ dân số":"177 người\/km²","hình":"","kinh giây":"30","vĩ độ":"21","kinh độ":"105","thời điểm dân số":"2019","web":"{{url|phudinh.dinhhoa.thainguyen.gov.vn}} }}","mã hành chính":"05602<ref>[https:\/\/danhmuchanhchinh.gso.gov.vn\/ Tổng cục Thống kê]<\/ref>","tên":"Phú Đình","vĩ phút":"48","mã bưu chính":"","ghi chú hình":""}]}}