{"1251760":{"Thông tin đơn vị hành chính Việt Nam":[{"diện tích":"16,97 km²","vĩ giây":"55","vùng":"[[Tây Nguyên]]","dân số":"7.204 người","thành lập":"12\/4\/2018<ref name=NQ493\/>","tỉnh":"[[Lâm Đồng]]","huyện":"[[Cát Tiên]]","trụ sở UBND":"","kinh phút":"19","mật độ dân số":"425 người\/km²","hình":"","kinh giây":"1","vĩ độ":"11","kinh độ":"107","thời điểm dân số":"2017","dân tộc":"","mã hành chính":"25180<ref>[https:\/\/danhmuchanhchinh.gso.gov.vn\/ Tổng cục Thống kê]<\/ref>","tên":"Phước Cát","vĩ phút":"34","mã bưu chính":"}}","ghi chú hình":""}]}}