{"853013":{"Thông tin đơn vị hành chính Việt Nam ":[{"diện tích":"1,21 km²","vùng":"[[Tây Nguyên]]","dân số":"17.795 người","thành lập":"1986<ref name=QD67\/>","tỉnh":"[[Lâm Đồng]]","trụ sở UBND":"","mật độ dân số":"14.707 người\/km²","hình":"Chùa Linh Sơn 2.jpg","thành phố":"[[Đà Lạt]]","vĩ độ":"11.949349","kinh độ":"108.435553","thời điểm dân số":"1999","dân tộc":"","mã hành chính":"24781<ref>[https:\/\/danhmuchanhchinh.gso.gov.vn\/ Tổng cục Thống kê]<\/ref>","tên":"Phường 2","mã bưu chính":"}}","ghi chú hình":"[[Chùa Linh Sơn (Đà Lạt)|Chùa Linh Sơn]] trên địa bàn phường 2"}]}}