{"19719668":{"thời gian sống":[{}],"Viên chức\n":[{"con":"","miêu tả":"","đảng":"[[Đảng Cộng sản Việt Nam]]","chú thích":"}}","phó chức vụ":"","hình":"","chữ ký":"","chồng":"","cỡ hình":"","dân tộc":"[[Người Kinh|Kinh]]","học trường":"","nơi ở":"","giáo dục":"","cha":"","đa số":"","website":"","phó viên chức":"","ngày chết":"10 tháng 5, 2007","nơi chết":"[[Thành phố Hồ Chí Minh]]","vợ":"","nghề nghiệp":"","chức vụ":"Bí thư [[Thành ủy Thành phố Hồ Chí Minh|Tỉnh ủy Gia Định]]","nơi sinh":"[[An Nhơn Tây]], [[Củ Chi]], [[Gia Định (tỉnh)|Gia Định]]","địa hạt":"{{VIE}}","đạo":"","bắt đầu":"[[Tháng 10]], [[1954]]","học vị":"","tên":"Phạm Khải","ngày sinh":"8 tháng 9, 1922","kế nhiệm":"[[Huỳnh Văn Thớm]]","kết thúc":"[[Tháng 7]], [[1957]]","họ hàng":"","kết hợp dân sự":"","tiền nhiệm":"[[Tô Ký]]"}]}}