{"25629":{"ngày mất và tuổi":[{}],"hlist":[{}],"Thông tin nghệ sĩ\n":[{"image":"Nhac si Pham Dinh Chuong.jpeg","caption":"","tên khai sinh":"Phạm Đình Chương","imagesize":"230px","ca khúc":"''[[Nửa hồn thương đau]]''<br>''[[Ly rượu mừng]]''<br> ''Đón xuân''","nghề nghiệp":"{{hlist|[[Nhạc sĩ]]|[[Ca sĩ]]}}","nơi mất":"[[California]], [[Hoa Kỳ]]","thành viên của":"[[Ban hợp ca Thăng Long]] }}","nghệ danh âm nhạc":"Hoài Bắc","ngày mất":"{{ngày mất và tuổi|1991|08|22|1929|11|14}}","dân tộc":"[[Người Kinh|Kinh]]","dòng nhạc":"{{hlist|[[Nhạc tiền chiến]]|[[Tình khúc 1954-1975]]}}","nhạc cụ":"[[Giọng hát]]","nơi sinh":"[[Hà Nội]], [[Bắc Kỳ]], [[Liên bang Đông Dương]]","tên":"Phạm Đình Chương","ngày sinh":"14 tháng 11, 1929","nền":"nhạc sĩ","giai đoạn sáng tác âm nhạc":"1946\u20131991"}]}}