{"555609":{"Thông tin đơn vị hành chính Việt Nam ":[{"diện tích":"5,45","vùng":"[[Bắc Trung Bộ]]","chủ tịch UBMTTQ":"","hình":"","kinh giây":"","kinh độ":"","thời điểm dân số":"","dân tộc":"","mã hành chính":"16069<ref>[https:\/\/danhmuchanhchinh.gso.gov.vn\/ Tổng cục Thống kê]<\/ref>","vĩ phút":"","mã bưu chính":"44329 }}","vị trí lấy tọa độ":"","vĩ giây":"","dân số":"4.669 người (1999)<ref name=QD19\/>; <br>4.329 người (2009)<ref name=\"HL\"\/>","thành lập":"","tỉnh":"[[Thanh Hóa]]","huyện":"[[Hậu Lộc]]","trụ sở UBND":"","kinh phút":"","mật độ dân số":"","thành phố":"","bí thư":"","vĩ độ":"","chủ tịch HĐND":"","tên":"Quang Lộc","chủ tịch UBND":"","ghi chú hình":"","thị xã":""}]}}