{"1251993":{"Địa phương lân cận\n":[{"Đông Bắc":"[[Sông Ray (xã)|Sông Ray]]","Giữa":"Quảng Thành","Bắc":"[[Xà Bang]]","Đông":"[[Lâm San]]","Đông Nam":"[[Xuân Sơn, Châu Đức|Xuân Sơn]], [[Sơn Bình, Châu Đức|Sơn Bình]]","Tây":"[[Kim Long, Châu Đức|Kim Long]], [[Bàu Chinh]]","Nam":"[[Bình Giã]], [[Bình Trung, Châu Đức|Bình Trung]]","Tây Bắc":"[[Xà Bang]] }}","Tây Nam":"[[Bình Giã]]"}],"Thông tin đơn vị hành chính Việt Nam ":[{"bản đồ 1":"{{Maplink|frame=yes|plain=yes|frame-width=280|frame-align=center|type=shape|fill=#ffffff|fill-opacity=0|stroke-width=3}}","diện tích":"30,88 km²","vĩ giây":"22","vùng":"[[Đông Nam Bộ]]","dân số":"9.227 người","thành lập":"1994<ref name=ND45\/>","tỉnh":"[[Bà Rịa \u2013 Vũng Tàu]]","huyện":"[[Châu Đức]]","trụ sở UBND":"","kinh phút":"17","mật độ dân số":"299 người\/km²","hình":"","kinh giây":"7","vĩ độ":"10","kinh độ":"107","thời điểm dân số":"1999","dân tộc":"","mã hành chính":"26605<ref>[https:\/\/danhmuchanhchinh.gso.gov.vn\/ Tổng cục Thống kê]<\/ref>","tên":"Quảng Thành","vĩ phút":"42","mã bưu chính":"}}","ghi chú hình":""}]}}