{"19664216":{"Huân chương VN":[{}],"ngày mất và tuổi":[{}],"thời gian sống":[{}],"Thông tin nghệ sĩ\n":[{"quốc tịch":"{{VIE}}","tiền tố":"[[Nghệ sĩ Ưu tú]]","tên khai sinh":"Đào Quốc Trụ","hình":"Quoc Tru.png","nghề nghiệp":"[[Nhà giáo]]<br>Nghệ sĩ Opera","nơi mất":"[[Bệnh viện 175]], [[Thành phố Hồ Chí Minh]], [[Việt Nam]]","khen thưởng":"{{Huân chương VN|Lao động|3}} }}","danh hiệu":"[[Nghệ sĩ Ưu tú]]","ngày mất":"{{ngày mất và tuổi|2021|8|14|1941|1|3}}","chức vụ":"Trưởng Khoa Thanh nhạc [[Nhạc viện Thành phố Hồ Chí Minh]]","dân tộc":"[[Người Việt|Kinh]]","nguyên nhân mất":"[[COVID-19]]","nơi sinh":"","bắt đầu":"1976","tên":"Đào Quốc Trụ","ngày sinh":"3 tháng 1, 1941","chú thích hình":"","kết thúc":"2001","nền":"nhạc sĩ"}]}}