{"442682":{"Thông tin đơn vị hành chính Việt Nam ":[{"bản đồ 1":"{{Maplink|frame=yes|plain=yes|frame-width=280|frame-align=center|type=shape|fill=#ffffff|fill-opacity=0|stroke-width=3}}","diện tích":"57,53 km²","vùng":"[[Đồng bằng sông Cửu Long]]","dân số":"2.534 người","thành lập":"1989<ref name=74-HĐBT\/>","tỉnh":"[[Long An]]","huyện":"[[Thạnh Hóa]]","trụ sở UBND":"","mật độ dân số":"44 người\/km²","hình":"","vĩ độ":"10.741094","kinh độ":"106.237348","thời điểm dân số":"1999","mã hành chính":"27871<ref>[https:\/\/danhmuchanhchinh.gso.gov.vn\/ Tổng cục Thống kê]<\/ref>","tên":"Thuận Bình","mã bưu chính":"}}","ghi chú hình":""}]}}