{"1253524":{"Thông tin đơn vị hành chính Việt Nam":[{"diện tích":"101,11 km²","vĩ giây":"6","vùng":"[[Đông Bắc Bộ]]","dân số":"4.790 người<ref name=HAGIANG2019\/>","thành lập":"","tỉnh":"[[Hà Giang]]","huyện":"[[Quang Bình]]","trụ sở UBND":"","kinh phút":"40","mật độ dân số":"47 người\/km²","hình":"","kinh giây":"8","vĩ độ":"22","kinh độ":"104","thời điểm dân số":"2019","web":"{{url|xtiennguyen.hagiang.gov.vn}} }}","mã hành chính":"01225<ref>[https:\/\/danhmuchanhchinh.gso.gov.vn\/ Tổng cục Thống kê]<\/ref>","tên":"Tiên Nguyên","vĩ phút":"30","mã bưu chính":"","ghi chú hình":""}]}}