{"19636330":{"Thông tin nghệ sĩ\n":[{"thể loại âm nhạc":"[[Nhạc cổ điển]]","kích thước hình":"180px","hợp tác với":"","quốc tịch":"{{VIE}}","tiền tố":"[[Nghệ sĩ Nhân dân]]","tên khai sinh":"Trần Thị Mơ","hình":"","ca khúc":"","vợ":"","nghệ danh":"","nghề nghiệp":"Nghệ sĩ Cello","nơi mất":"","khen thưởng":"","danh hiệu":"{{Br list|[[Nghệ sĩ ưu tú]] (2001) |[[Nghệ sĩ nhân dân]] (2015)}}","tên gốc":"","ngày mất":"","nguyên quán":"}}","nơi sinh":"[[Thái Nguyên]]","name":"Trần Thị Mơ","ngày sinh":"4 tháng 4 năm 1959 (62 tuổi)","chú thích hình":"","nền":"Nhạc công"}]}}