{"3698782":{"Viên chức \n":[{"con":"","đảng":"[[Đảng Cộng sản Việt Nam]] }}","chức vụ 3":"","chết":"","chức vụ 2":"Phó Giám đốc Sở Lao động - Thương binh và xã hội tỉnh Bến Tre","kế nhiệm 3":"","hình":"","tiền nhiệm 2":"","kế nhiệm 2":"","tiền nhiệm 3":"","chồng":"","dân tộc":"[[Người Việt|Kinh]]","nơi ở":"","cha":"","học vấn":"*Cử nhân chuyên ngành [[Xã hội học]] *Thạc sĩ công tác xã hội","kết thúc 3":"","date2":"2021","date1":"2016","ngày chết":"","mẹ":"","nơi chết":"","vợ":"","nghề nghiệp":"[[chính trị gia]]","bắt đầu 2":"","bắt đầu 3":"","chức vụ":"[[Đại biểu Quốc hội Việt Nam]]","nơi sinh":"ấp Thới Hoà, xã [[Châu Hòa]], huyện [[Giồng Trôm]], tỉnh [[Bến Tre]], [[Việt Nam]]","đạo":"[[Không tôn giáo|Không]]","tên":"Trần Thị Thanh Lam","ngày sinh":"{{ngày sinh và tuổi|1979|9|29}}","kế nhiệm":"","kết thúc 2":"","ngang":"","tiền nhiệm":""}],"thời gian sống":[{}],"ngày sinh và tuổi":[{}]}}