{"317187":{"Thời gian sống":[{"{{Thời gian sống|Sinh":"1952}}"}],"Thông tin nhạc sĩ \n":[{"Ngày sinh":"[[1952]]","Nghệ sĩ liên quan":"}}","Tên khai sinh":"Nguyễn Tuấn Phong","spouse":"Đỗ Thị Tuyết Nam","Nhạc cụ":"[[Hát]]","Chú thích hình":"","Kiểu giọng":"Nam cao","Kích cỡ":"","Quê quán":"[[Hà Nội]], [[Việt Nam]]","Ngày mất":"","Tên nghệ sĩ":"Tuấn Phong","Nghề nghiệp":"[[Ca sĩ]], [[giảng viên]]","Năm hoạt động":"1968-nay","Hình":"","Thể loại":"nhạc đỏ, nhạc thính phòng","Phong cảnh":"","Nghệ danh":"Tuấn Phong","Nền":""}]}}