{"1252846":{"Thông tin đơn vị hành chính Việt Nam\n":[{"diện tích":"8,55 km²<ref name=MS\/>","vĩ giây":"6","vùng":"[[Đồng bằng sông Hồng]]","dân số":"6.877 người<ref name=MS\/>","thành lập":"2003<ref>Nghị định 107\/2003\/NĐ-CP<\/ref>","huyện":"[[Thạch Thất]]","trụ sở UBND":"","kinh phút":"32","mật độ dân số":"804 người\/km²","hình":"","kinh giây":"35","thành phố":"[[Hà Nội]]","bí thư":"Nguyễn Đình Tùng|chủ tịch HĐND=Nguyễn Đình Tùng}}","vĩ độ":"21","kinh độ":"105","thời điểm dân số":"2021","dân tộc":"[[Kinh]]","vai trò hành chính":"xã","mã hành chính":"10000<ref>[https:\/\/danhmuchanhchinh.gso.gov.vn\/ Tổng cục Thống kê]<\/ref>","tên":"Tân Xã","vĩ phút":"1","mã bưu chính":"","ghi chú hình":""}]}}