{"1609773":{"Thông tin nhân vật\n":[{"tên khác":"","phong trào":"","tên khai sinh":"","giải thưởng":"*Giải thưởng Hellman\/Hammett năm 2011 của [[Tổ chức Theo dõi Nhân quyền]] *Giải ''Phụ nữ Can đảm Thế giới'' năm 2011 của [[Bộ Ngoại giao Hoa Kỳ]] *Giải Nhân quyền Việt Nam 2012 của [[Mạng lưới Nhân quyền Việt Nam]]","hình":"","cư trú":"{{USA}}","nơi mất":"","quê quán":"[[Bạc Liêu]], [[Việt Nam]]","chữ ký":"}}","cỡ hình":"","dân tộc":"[[Người Việt|Kinh]]","đối tác":"","loại":"","học vấn":"","height":"","vợ (chồng)":"","công việc":"sĩ quan công an, người viết blog","tôn giáo":"","cha mẹ":"Đặng Thị Kim Liêng ( -2012)","module":"","kỷ nguyên":"","weight":"","giáo phái":"","tuyển dụng":"","danh hiệu":"","nổi tiếng":"[[Người bất đồng chính kiến|Nhân vật Bất đồng chính kiến]] ở Việt Nam","đối thủ":"","tên":"Tạ Phong Tần","ngày sinh":"[[1968]]","tổ chức":"","con cái":"","tiền nhiệm":"","tài sản":"","hội đồng":"","ngày mất":"","người thân":"","notable_works":"Blog ''Công lý và Sự thật''","module5":"","cáo buộc":"''\"tuyên truyền chống nhà nước\"''","module4":"","website":"http:\/\/conglysuthat.blogspot.com\/","module6":"","nguyên nhân cái chết":"","quốc tịch":"{{VIE}}","tiêu đề":"","mức phạt":"10 năm tù giam","nhiệm kỳ":"","module3":"","module2":"","đại lý":"","đảng phái":"[[Tập tin:Flag of the Communist Party of Vietnam.svg|22px]] [[Đảng Cộng sản Việt Nam]] (đến 2006)","nơi sinh":"huyện [[Vĩnh Lợi]], [[Bạc Liêu]], [[Việt Nam Cộng hòa]]","học vị":"","kế nhiệm":"","ghi chú hình":""}]}}