{"9803":{"fact":[{"{{fact|date":"7-2014}}"}],"Thông tin ngày lễ \n":[{"date":"Ngày 15 tháng 8 [[âm lịch]]","image":"Mid-Autumn_Festival-beijing.jpg","official_name":"Tết Trung Thu","caption":"Tết Trung thu tại [[Bắc Kinh]]","litcolor":"","imagesize":"222px","type":"asian festival","holiday_name":"Tết Trung thu","begins":"[[Nhà Đường]] (?)","significance":"","date{{#time:Y|last year}}":"{{#time:l, \"ngày\" j \"tháng\" n|{{Âm lịch|A2D|D=15|M=8|Y={{#time:Y|last year}}|df=d-m-y|utc=7}}}}","ends":"","nickname":"Tết Thiếu nhi, Tết Trẻ con<ref name=\"vnpt\">Việt Nam phong tục, Phan Kế Bính<\/ref>","longtype":"[[Lễ hội]] văn hóa, quốc gia."}],"cite news":[{"{{cite news|date":"10 August 2014|title=Back to Basics: Baked Traditional Moon Cakes|website=Guai Shu Shu|url=https:\/\/kwgls.wordpress.com\/2014\/08\/10\/back-to-basicsbaked-traditional-mooncake-%E4%BC%A0%E7%BB%9F%E7%B2%A4%E5%BC%8F%E6%9C%88%E9%A5%BC%EF%BC%89\/|access-date=4 October 2017}}"}]}}