{"1253572":{"Thông tin đơn vị hành chính Việt Nam\n":[{"diện tích":"17,72 km²<ref name=MS\/>","vĩ giây":"37","vùng":"[[Duyên hải Nam Trung Bộ]]","dân số":"12.383 người<ref name=MS\/>","thành lập":"2013","tỉnh":"[[Quảng Ngãi]]","trụ sở UBND":"","kinh phút":"52","mật độ dân số":"699 người\/km²","hình":"","kinh giây":"54","thành phố":"[[Quảng Ngãi (thành phố)|Quảng Ngãi]]","vĩ độ":"15","kinh độ":"108","thời điểm dân số":"1999","vai trò hành chính":"Xã","mã hành chính":"21187<ref>[https:\/\/danhmuchanhchinh.gso.gov.vn\/ Tổng cục Thống kê]<\/ref>","tên":"Tịnh Hòa","vĩ phút":"12","mã bưu chính":"}}","ghi chú hình":""}]}}