{"577573":{"Thời gian sống":[{}],"infobox musical artist\n":[{"thể loại":"[[Nhạc trẻ]], [[nhạc trữ tình]], [[pop]], [[ballad]], [[blues]], [[jazz]], [[R&B]]","hợp tác với":"[[Quốc Trung]], [[Huy Tuấn]], [[Lưu Thiên Hương]], Dũng dAlAt, [[Đức Trí]], Trang, [[Văn Mai Hương]], [[Trung Quân Idol]], [[Hồ Trung Dũng]], [[Quốc Thiên]], [[Quang Linh]]","năm hoạt động":"2005 - nay","embed":"yes","hãng đĩa":"Thanh Việt Production}}"}],"birth date and age":[{}],"Thông tin nhân vật \n":[{"image":"Uyen Linh Singer.jpg","tên khác":"Báo Mắt Biếc","hợp tác với":"[[Quốc Trung]], [[Huy Tuấn]], [[Lưu Thiên Hương]], Dũng dAlAt, [[Đức Trí]], Trang, [[Văn Mai Hương]], [[Trung Quân Idol]], [[Hồ Trung Dũng]], [[Quốc Thiên]], [[Quang Linh]]","module":"{{infobox musical artist","caption":"Uyên Linh, tháng 8 năm 2013","tên khai sinh":"Trần Nguyễn Uyên Linh","nghề nghiệp":"[[Ca sĩ]], [[nhà sản xuất âm nhạc]]","hãng đĩa":"Thanh Việt Production}} }}","thể loại":"[[Nhạc trẻ]], [[nhạc trữ tình]], [[pop]], [[ballad]], [[blues]], [[jazz]], [[R&B]]","nơi sinh":"[[Thành phố Hồ Chí Minh]], [[Việt Nam]]<ref>Gia đình Uyên Linh sống ở [[Thành phố Hồ Chí Minh]] và Uyên Linh cũng sinh ra và lớn lên tại đây. Clip: http:\/\/www.youtube.com\/watch?v=BzHs2r016Qk<\/ref>","tên":"Uyên Linh","ngày sinh":"{{birth date and age|1987|12|31}}<ref>Uyên Linh từng trả lời người hâm mộ trên trang mạng xã hội của mình rằng cô tuổi mèo, nên ngày sinh của cô sẽ là 31\/12\/1987 chứ không phải 31\/12\/1988 như nhiều bài đã viết<\/ref>","năm hoạt động":"2005 - nay","embed":"yes"}]}}