{"3367630":{"Thông tin nhân vật\n":[{"image":"","occupation":"[[Diễn viên]]","birth_name":"Nguyễn Văn Liêm","birth_date":"{{ngày sinh và tuổi|1956|6|11}}","quốc tịch":"{{VIE}}","caption":"","birth_place":"[[Sài Gòn]], [[Việt Nam Cộng hòa]]","years_active":"1974 - nay","nghệ danh":"Việt Anh","death_date":"","children":"1 }}","awards":"Mai vàng 1995<br \/>[[Nghệ sĩ ưu tú]] 2001<br \/>Cù nèo vàng 2011<br \/>[[Nghệ sĩ nhân dân]] 2019","name":"Việt Anh","death_place":""}],"thời gian sống":[{}],"ngày sinh và tuổi":[{}]}}