{"1254146":{"Thông tin đơn vị hành chính Việt Nam":[{"bản đồ 1":"{{Maplink|frame=yes|plain=yes|frame-width=280|frame-align=center|type=shape|fill=#ffffff|fill-opacity=0|stroke-width=3}}","diện tích":"102,73 km²","vĩ giây":"20","vùng":"[[Đồng bằng sông Cửu Long]]","dân số":"6.635 người<ref name=KIENGIANG2020\/>","thành lập":"7\/2\/2005<ref name=15\/2005\/NĐ-CP\/>","tỉnh":"[[Kiên Giang]]","huyện":"[[Giang Thành]]","trụ sở UBND":"","kinh phút":"41","mật độ dân số":"65 người\/km²","hình":"","kinh giây":"2","bí thư":"Trần Quang Thái","vĩ độ":"10","chủ tịch HĐND":"Trần Thanh Tiền","kinh độ":"104","thời điểm dân số":"2020","mã hành chính":"30793<ref>[https:\/\/danhmuchanhchinh.gso.gov.vn\/ Tổng cục Thống kê]<\/ref>","tên":"Vĩnh Điều","vĩ phút":"28","chủ tịch UBND":"Trần Quang Thái","mã bưu chính":"}}","ghi chú hình":""}]}}