{"1243782":{"Thông tin đơn vị hành chính Việt Nam":[{"diện tích":"4,84 km²<ref name=MS\/>","vĩ giây":"47","vùng":"[[Bắc Trung Bộ]]","dân số":"3.874 người<ref name=MS\/>","thành lập":"1991<ref>516\/1991\/QĐ-TCCP<\/ref>","tỉnh":"[[Quảng Trị]]","trụ sở UBND":"Đường Huyền Trân Công Chúa, khu phố 4","kinh phút":"04","mật độ dân số":"800 người\/km²","hình":"","kinh giây":"34","thành phố":"[[Đông Hà]]","vĩ độ":"16","kinh độ":"107","thời điểm dân số":"2010","mã hành chính":"19339<ref>[https:\/\/danhmuchanhchinh.gso.gov.vn\/ Tổng cục Thống kê]<\/ref>","tên":"Đông Thanh","vĩ phút":"49","mã bưu chính":"}}","ghi chú hình":""}]}}