{"13816291":{"Thông tin đường bộ Việt Nam\n":[{"caption_bản_đồ":"","Đường":"","Chiều dài":"89,5 km","Cuối":"{{Tỉnh lộ Việt Nam|108|link=1}} tại Km 8+980, [[Co Mạ]], [[Thuận Châu]]","điều hành":"Sở Giao thông Vận tải tỉnh Sơn La","Giữa":"","Hướng cuối":"Tây","caption_đường":"","Hướng đầu":"Đông","Tồn tại":"","Tỉnh":"[[Sơn La]]","hình chụp đường":"","logo caption":"","Tên khác":"Tỉnh lộ 113","logo":"","tên":"Đường tỉnh 113","Đầu":"{{Banner đường Việt Nam|QL|4G|link=1}} tại Km 35+160, [[Nà Ớt]], [[Mai Sơn]]","hình bản đồ":"","Trạng thái":"Đang hoạt động","Q_H":"[[Mai Châu]], [[Thuận Châu]]","DB_Trước":"{{Tỉnh lộ Việt Nam|112|link=1}}","Thành phố":"","DB_Sau":"{{Tỉnh lộ Việt Nam|114|link=1}} }}"}],"Tỉnh lộ Việt Nam":[{"{{Tỉnh lộ Việt Nam|114|link":"1}}"}]}}