{"1262758":{"Thông tin đơn vị hành chính Việt Nam\n":[{"diện tích":"8,97 km²<ref name=MS\/>","vĩ giây":"28","vùng":"[[Đông Bắc Bộ]]","dân số":"3019 người<ref name=MS\/>","thành lập":"","tỉnh":"[[Phú Thọ]]","huyện":"[[Thanh Ba]]","trụ sở UBND":"","kinh phút":"10","mật độ dân số":"337 người\/km²","hình":"","kinh giây":"59","vĩ độ":"21","kinh độ":"105","thời điểm dân số":"1999","dân tộc":"","vai trò hành chính":"Xã","mã hành chính":"08161<ref>[https:\/\/danhmuchanhchinh.gso.gov.vn\/ Tổng cục Thống kê]<\/ref>","tên":"Đại An","vĩ phút":"31","mã bưu chính":"}}","ghi chú hình":""}]}}