{"1243801":{"Thông tin đơn vị hành chính Việt Nam":[{"diện tích":"3,58 km²<ref name=HUNGYEN2019\/>","vĩ giây":"25","vùng":"[[Đồng bằng sông Hồng]]","dân số":"5.074 người<ref name=HUNGYEN2019\/>","thành lập":"","tỉnh":"[[Hưng Yên]]","huyện":"[[Khoái Châu]]","trụ sở UBND":"","kinh phút":"01","mật độ dân số":"1.417 người\/km²","hình":"","kinh giây":"15","vĩ độ":"20","kinh độ":"106","thời điểm dân số":"1999","mã hành chính":"12241<ref>[https:\/\/danhmuchanhchinh.gso.gov.vn\/ Tổng cục Thống kê]<\/ref>","tên":"Đồng Tiến","vĩ phút":"50","mã bưu chính":"}}","ghi chú hình":""}]}}