{"1243811":{"Thông tin đơn vị hành chính Việt Nam":[{"diện tích":"11,81 km²","vĩ giây":"40","vùng":"[[Tây Bắc Bộ]]","dân số":"3.575 người","thành lập":"","tỉnh":"[[Lào Cai]]","trụ sở UBND":"","kinh phút":"56","mật độ dân số":"303 người\/km²","hình":"","kinh giây":"48","thành phố":"[[Lào Cai (thành phố)|Lào Cai]]","vĩ độ":"22","kinh độ":"103","thời điểm dân số":"2019","web":"{{url|dongtuyen.tplaocai.laocai.gov.vn}} }}","mã hành chính":"02662<ref>[https:\/\/danhmuchanhchinh.gso.gov.vn\/ Tổng cục Thống kê]<\/ref>","tên":"Đồng Tuyển","vĩ phút":"29","mã bưu chính":"","ghi chú hình":""}]}}