{"1249711":{"Thông tin đơn vị hành chính Việt Nam":[{"diện tích":"133,49 km²<ref name=MS\/>","vĩ giây":"6","vùng":"[[Tây Nguyên]]","dân số":"2.919 người<ref name=MS\/>","thành lập":"2000<ref>[http:\/\/vbpq.mine.vn\/VanBan\/ToanVan\/5926\/nghi-dinh-672000nd-cp.html Nghị định 67\/2000\/NĐ-CP]{{Liên kết hỏng|date=2021-03-13 |bot=InternetArchiveBot }}<\/ref>","tỉnh":"[[Gia Lai]]","huyện":"[[Krông Pa]]","trụ sở UBND":"","kinh phút":"38","mật độ dân số":"22 người\/km²","hình":"","kinh giây":"2","vĩ độ":"13","kinh độ":"108","thời điểm dân số":"2000","mã hành chính":"24100<ref>[https:\/\/danhmuchanhchinh.gso.gov.vn\/ Tổng cục Thống kê]<\/ref>","tên":"Ia HDreh","vĩ phút":"5","mã bưu chính":"}}","ghi chú hình":""}]}}