{"25118":{"Thời gian sống":[{}],"Infobox musical artist":[{"website":"}}","background":"solo_singer","genre":"{{flat list| *[[V-pop]] *[[Ballad]] *[[Dance]] *[[R&B]] *[[Pop rock]] *[[Pop soul]] }}","associated_acts":"","instrument":"{{hlist|[[Hát]]|[[Piano]]|[[Guitar]]|[[:en:Recorder (musical instrument)|Sáo recorder]]|[[:en:Guzheng|Cổ tranh]]}}","years_active":"1999\u2013nay<ref name=\"Tâm-Tuổi trẻ\">{{chú thích web |url=http:\/\/tuoitre.vn\/tin\/van-hoa-giai-tri\/am-nhac\/20130406\/vi-do-la-tam\/541576.html |tiêu đề=Vì đó là Tâm! |author=Quỳnh Nguyễn |ngày=6 tháng 4 năm 2013 |ngày truy cập=ngày 16 tháng 9 năm 2015 |publisher=[[Đoàn Thanh niên Cộng sản Hồ Chí Minh]] |work=[[Tuổi Trẻ (báo)|Tuổi Trẻ]] |ngôn ngữ= |archive-date=2014-12-31 |archive-url=https:\/\/web.archive.org\/web\/20141231001551\/http:\/\/tuoitre.vn\/tin\/van-hoa-giai-tri\/am-nhac\/20130406\/vi-do-la-tam\/541576.html |url-status=live }}<\/ref>","label":"{{flat list| *Hãng phim Phương Nam *MT Entertainment }}","{{Infobox musical artist|embed":"yes"}],"birth date and age":[{}],"hlist":[{}],"Imdb name":[{}]}}