{"1250806":{"Thông tin đơn vị hành chính Việt Nam":[{"diện tích":"9,40 km²","vĩ giây":"19","vùng":"[[Bắc Trung Bộ]]","dân số":"2.899 người<ref name=QBINH2019\/>","thành lập":"","tỉnh":"[[Quảng Bình]]","huyện":"[[Bố Trạch]]","trụ sở UBND":"","kinh phút":"24","mật độ dân số":"308 người\/km²","hình":"","kinh giây":"20","vĩ độ":"17","kinh độ":"106","thời điểm dân số":"2019","mã hành chính":"19120<ref>[https:\/\/danhmuchanhchinh.gso.gov.vn\/ Tổng cục Thống kê]<\/ref>","tên":"Mỹ Trạch","vĩ phút":"42","mã bưu chính":"}}","ghi chú hình":""}]}}