{"1251270":{"Thông tin đơn vị hành chính Việt Nam":[{"diện tích":"10,23 km²<ref name=MS\/>","vĩ giây":"0","vùng":"[[Duyên hải Nam Trung Bộ]]","dân số":"11.386 người<ref name=MS\/>","thành lập":"","tỉnh":"[[Bình Định]]","trụ sở UBND":"","kinh phút":"1","mật độ dân số":"1.113 người\/km²","hình":"","kinh giây":"8","vĩ độ":"13","kinh độ":"109","thời điểm dân số":"1999","mã hành chính":"21931<ref>[https:\/\/danhmuchanhchinh.gso.gov.vn\/ Tổng cục Thống kê]<\/ref>","tên":"Nhơn Phúc","vĩ phút":"54","mã bưu chính":"}}","ghi chú hình":"","thị xã":"[[An Nhơn]]"}]}}