{"1253942":{"Thông tin đơn vị hành chính Việt Nam":[{"diện tích":"32,92 km²<ref name=MS\/>","vĩ giây":"30","vùng":"[[Bắc Trung Bộ]]","dân số":"8.728 người<ref name=MS\/>","thành lập":"2009<ref>07\/NĐ-CP(2009)<\/ref>","tỉnh":"[[Nghệ An]]","huyện":"[[Anh Sơn]]","trụ sở UBND":"","kinh phút":"0","mật độ dân số":"265 người\/km²","hình":"","kinh giây":"40","vĩ độ":"18","kinh độ":"105","thời điểm dân số":"1999","mã hành chính":"17356<ref>[https:\/\/danhmuchanhchinh.gso.gov.vn\/ Tổng cục Thống kê]<\/ref>","tên":"Tường Sơn","vĩ phút":"57","mã bưu chính":"}}","ghi chú hình":""}]}}