{"324190":{"Ngày sinh và tuổi":[{"{{Ngày sinh và tuổi|mf":"yes|1978|6|30}}"}],"Thanh chủ đề":[{}],"Thời gian sống":[{}],"Infobox musical artist":[{"background":"non_vocal_instrumentalist","genre":"{{flatlist| * [[Pop]] * [[Jazz]] * [[Ambient]] * [[New-age (nhạc)|New-age]] }}","associated_acts":"{{flatlist| * Ban nhạc Sao Mai * [[Ngọc Châu (nhạc sĩ)|Ngọc Châu]] * [[Trần Thu Hà]] * [[Tấn Minh]] * [[Nguyên Thảo]] * [[Tùng Dương]] * [[Hoàng Quyên]] * Nguyễn Nhất Lý * Võ Vân Ánh }} }}","instrument":"{{flatlist| * [[Piano]] * [[Organ (nhạc cụ)|Organ]] * [[Keyboard (nhạc cụ)|Keyboard]] * [[Synthesizer]] }}","label":"{{flatlist| * [[Viết Tân Records]] * [[Hãng phim Phương Nam]] }}","{{Infobox musical artist|embed":"yes"}],"quote box":[{"{{quote box|quote":"\"Bảo thấy cuộc sống trần trụi, hiểu những bi kịch của thời đại. Cũng như tôi, Bảo là một người buồn, nhưng thay vì chế nhạo, giễu cợt hoặc đấu tranh với những cái xấu cho một sự thức tỉnh, Bảo chọn cách nhắn nhủ, nhắc nhớ về những giá trị tốt đẹp của con người như tình yêu và lương tâm. Thái độ sống và viết của Bảo trung thành với quan điểm đó.\"<ref name=\"vietnamnet\" \/>|source=\u2014 Trần Thu Hà|width=25%|align=right|style=padding:8px;}}"}],"marriage":[{}]}}